<!--Copyright 2013 MLB Advanced Media, L.P.  Use of any content on this page acknowledges agreement to the terms posted here http://gdx.mlb.com/components/copyright.txt--><game venue="Oriole Park at Camden Yards" date="September 26, 2013">
	<team type="away" id="TOR" name="Toronto Blue Jays">
		<player id="450317" first="J.P." last="Arencibia" num="9" boxname="Arencibia" rl="R" position="C" current_position="C" status="A" team_abbrev="TOR" team_id="141" parent_team_abbrev="TOR" parent_team_id="141" bat_order="6" game_position="C" avg=".194" hr="21" rbi="54"/>
		<player id="279824" first="Mark" last="Buehrle" num="56" boxname="Buehrle" rl="L" position="P" current_position="P" status="A" team_abbrev="TOR" team_id="141" parent_team_abbrev="TOR" parent_team_id="141" bat_order="0" game_position="P" avg=".000" hr="0" rbi="0" wins="12" losses="9" era="4.09"/>
		<player id="434658" first="Rajai" last="Davis" num="11" boxname="Davis, R" rl="R" position="RF" status="A" team_abbrev="TOR" team_id="141" parent_team_abbrev="TOR" parent_team_id="141" avg=".260" hr="6" rbi="24"/>
		<player id="136660" first="Mark" last="DeRosa" num="16" boxname="DeRosa" rl="R" position="3B" status="A" team_abbrev="TOR" team_id="141" parent_team_abbrev="TOR" parent_team_id="141" avg=".234" hr="7" rbi="34"/>
		<player id="447755" first="Steve" last="Delabar" num="50" boxname="Delabar" rl="R" position="P" current_position="P" status="A" team_abbrev="TOR" team_id="141" parent_team_abbrev="TOR" parent_team_id="141" avg=".000" hr="0" rbi="0" wins="5" losses="5" era="3.34"/>
		<player id="285079" first="R.A." last="Dickey" num="43" boxname="Dickey" rl="R" position="P" status="A" team_abbrev="TOR" team_id="141" parent_team_abbrev="TOR" parent_team_id="141" avg=".333" hr="0" rbi="1" wins="13" losses="13" era="4.27"/>
		<player id="475138" first="Kyle" last="Drabek" num="4" boxname="Drabek" rl="R" position="P" status="A" team_abbrev="TOR" team_id="141" parent_team_abbrev="TOR" parent_team_id="141" avg=".000" hr="0" rbi="0" wins="0" losses="0" era="7.71"/>
		<player id="572365" first="Ryan" last="Goins" num="17" boxname="Goins" rl="R" position="SS" current_position="2B" status="A" team_abbrev="TOR" team_id="141" parent_team_abbrev="TOR" parent_team_id="141" bat_order="8" game_position="2B" avg=".255" hr="1" rbi="5"/>
		<player id="543238" first="Anthony" last="Gose" num="8" boxname="Gose" rl="L" position="RF" current_position="CF" status="A" team_abbrev="TOR" team_id="141" parent_team_abbrev="TOR" parent_team_id="141" bat_order="5" game_position="CF" avg=".260" hr="2" rbi="10"/>
		<player id="457918" first="J.A." last="Happ" num="48" boxname="Happ" rl="L" position="P" status="A" team_abbrev="TOR" team_id="141" parent_team_abbrev="TOR" parent_team_id="141" avg=".000" hr="0" rbi="0" wins="4" losses="7" era="4.85"/>
		<player id="445163" first="Casey" last="Janssen" num="44" boxname="Janssen" rl="R" position="P" status="A" team_abbrev="TOR" team_id="141" parent_team_abbrev="TOR" parent_team_id="141" avg=".000" hr="0" rbi="0" wins="4" losses="1" era="2.56"/>
		<player id="502026" first="Jeremy" last="Jeffress" num="33" boxname="Jeffress" rl="R" position="P" status="A" team_abbrev="TOR" team_id="141" parent_team_abbrev="TOR" parent_team_id="141" avg=".000" hr="0" rbi="0" wins="1" losses="0" era="1.08"/>
		<player id="554432" first="Chad" last="Jenkins" num="64" boxname="Jenkins" rl="R" position="P" current_position="P" status="A" team_abbrev="TOR" team_id="141" parent_team_abbrev="TOR" parent_team_id="141" avg=".000" hr="0" rbi="0" wins="1" losses="0" era="3.07"/>
		<player id="493128" first="Munenori" last="Kawasaki" num="66" boxname="Kawasaki" rl="R" position="SS" current_position="DH" status="A" team_abbrev="TOR" team_id="141" parent_team_abbrev="TOR" parent_team_id="141" bat_order="2" game_position="DH" avg=".237" hr="1" rbi="24"/>
		<player id="407798" first="Ryan" last="Langerhans" num="18" boxname="Langerhans" rl="L" position="LF" current_position="1B" status="A" team_abbrev="TOR" team_id="141" parent_team_abbrev="TOR" parent_team_id="141" bat_order="7" game_position="1B" avg=".000" hr="0" rbi="0"/>
		<player id="543434" first="Brett" last="Lawrie" num="13" boxname="Lawrie" rl="R" position="3B" current_position="3B" status="A" team_abbrev="TOR" team_id="141" parent_team_abbrev="TOR" parent_team_id="141" bat_order="3" game_position="3B" avg=".247" hr="11" rbi="43"/>
		<player id="452252" first="Adam" last="Lind" num="26" boxname="Lind" rl="L" position="1B" status="A" team_abbrev="TOR" team_id="141" parent_team_abbrev="TOR" parent_team_id="141" avg=".285" hr="23" rbi="64"/>
		<player id="571901" first="Aaron" last="Loup" num="62" boxname="Loup" rl="L" position="P" status="A" team_abbrev="TOR" team_id="141" parent_team_abbrev="TOR" parent_team_id="141" avg=".000" hr="0" rbi="0" wins="4" losses="6" era="2.49"/>
		<player id="430661" first="Dustin" last="McGowan" num="29" boxname="McGowan" rl="R" position="P" status="A" team_abbrev="TOR" team_id="141" parent_team_abbrev="TOR" parent_team_id="141" avg=".000" hr="0" rbi="0" wins="0" losses="0" era="2.19"/>
		<player id="435081" first="Mike" last="Nickeas" num="15" boxname="Nickeas" rl="R" position="C" status="A" team_abbrev="TOR" team_id="141" parent_team_abbrev="TOR" parent_team_id="141" avg=".000" hr="0" rbi="0"/>
		<player id="119984" first="Darren" last="Oliver" num="38" boxname="Oliver, D" rl="L" position="P" status="A" team_abbrev="TOR" team_id="141" parent_team_abbrev="TOR" parent_team_id="141" avg=".000" hr="0" rbi="0" wins="3" losses="4" era="3.94"/>
		<player id="469802" first="Luis" last="Perez" num="47" boxname="Perez, L" rl="L" position="P" status="A" team_abbrev="TOR" team_id="141" parent_team_abbrev="TOR" parent_team_id="141" avg=".000" hr="0" rbi="0" wins="0" losses="1" era="4.50"/>
		<player id="607680" first="Kevin" last="Pillar" num="22" boxname="Pillar" rl="R" position="CF" current_position="LF" status="A" team_abbrev="TOR" team_id="141" parent_team_abbrev="TOR" parent_team_id="141" bat_order="9" game_position="LF" avg=".186" hr="2" rbi="11"/>
		<player id="445170" first="Todd" last="Redmond" num="58" boxname="Redmond" rl="R" position="P" status="A" team_abbrev="TOR" team_id="141" parent_team_abbrev="TOR" parent_team_id="141" avg=".000" hr="0" rbi="0" wins="4" losses="2" era="3.77"/>
		<player id="408314" first="Jose" last="Reyes" num="7" boxname="Reyes" rl="R" position="SS" current_position="SS" status="A" team_abbrev="TOR" team_id="141" parent_team_abbrev="TOR" parent_team_id="141" bat_order="1" game_position="SS" avg=".296" hr="10" rbi="36"/>
		<player id="469134" first="Esmil" last="Rogers" num="32" boxname="Rogers, E" rl="R" position="P" status="A" team_abbrev="TOR" team_id="141" parent_team_abbrev="TOR" parent_team_id="141" avg=".000" hr="0" rbi="0" wins="5" losses="9" era="4.77"/>
		<player id="460069" first="Ricky" last="Romero" num="24" boxname="Romero, R" rl="L" position="P" status="A" team_abbrev="TOR" team_id="141" parent_team_abbrev="TOR" parent_team_id="141" avg=".000" hr="0" rbi="0" wins="0" losses="2" era="11.05"/>
		<player id="435045" first="Sergio" last="Santos" num="21" boxname="Santos, S" rl="R" position="P" status="A" team_abbrev="TOR" team_id="141" parent_team_abbrev="TOR" parent_team_id="141" avg=".000" hr="0" rbi="0" wins="1" losses="1" era="1.57"/>
		<player id="501213" first="Moises" last="Sierra" num="14" boxname="Sierra" rl="R" position="RF" current_position="RF" status="A" team_abbrev="TOR" team_id="141" parent_team_abbrev="TOR" parent_team_id="141" bat_order="4" game_position="RF" avg=".290" hr="1" rbi="11"/>
		<player id="489365" first="Josh" last="Thole" num="30" boxname="Thole" rl="R" position="C" status="A" team_abbrev="TOR" team_id="141" parent_team_abbrev="TOR" parent_team_id="141" avg=".179" hr="1" rbi="8"/>
		<player id="474599" first="Neil" last="Wagner" num="45" boxname="Wagner" rl="R" position="P" status="A" team_abbrev="TOR" team_id="141" parent_team_abbrev="TOR" parent_team_id="141" avg=".000" hr="0" rbi="0" wins="2" losses="4" era="3.75"/>
		<player id="430832" first="Jose" last="Bautista" num="19" boxname="Bautista" rl="R" position="RF" status="D15" team_abbrev="TOR" team_id="141" parent_team_abbrev="TOR" parent_team_id="141" avg=".259" hr="28" rbi="73"/>
		<player id="429665" first="Edwin" last="Encarnacion" num="10" boxname="Encarnacion" rl="R" position="1B" status="D15" team_abbrev="TOR" team_id="141" parent_team_abbrev="TOR" parent_team_id="141" avg=".272" hr="36" rbi="104"/>
		<player id="458675" first="Colby" last="Rasmus" num="28" boxname="Rasmus, C" rl="L" position="CF" status="D15" team_abbrev="TOR" team_id="141" parent_team_abbrev="TOR" parent_team_id="141" avg=".276" hr="22" rbi="66"/>
		<player id="466320" first="Melky" last="Cabrera" num="53" boxname="Cabrera, Me" rl="L" position="LF" status="D60" team_abbrev="TOR" team_id="141" parent_team_abbrev="TOR" parent_team_id="141" avg=".279" hr="3" rbi="30"/>
		<player id="446399" first="Brett" last="Cecil" num="27" boxname="Cecil" rl="L" position="P" status="D60" team_abbrev="TOR" team_id="141" parent_team_abbrev="TOR" parent_team_id="141" avg=".000" hr="0" rbi="0" wins="5" losses="1" era="2.82"/>
		<player id="430895" first="Maicer" last="Izturis" num="3" boxname="Izturis, M" rl="R" position="3B" status="D60" team_abbrev="TOR" team_id="141" parent_team_abbrev="TOR" parent_team_id="141" avg=".236" hr="5" rbi="32"/>
		<player id="435178" first="Josh" last="Johnson" num="55" boxname="Johnson, Jo" rl="R" position="P" status="D60" team_abbrev="TOR" team_id="141" parent_team_abbrev="TOR" parent_team_id="141" avg=".000" hr="0" rbi="0" wins="2" losses="8" era="6.20"/>
		<player id="453344" first="Brandon" last="Morrow" num="23" boxname="Morrow" rl="R" position="P" status="D60" team_abbrev="TOR" team_id="141" parent_team_abbrev="TOR" parent_team_id="141" avg=".000" hr="0" rbi="0" wins="2" losses="3" era="5.63"/>
		<player id="150009" first="Ramon" last="Ortiz" num="34" boxname="Ortiz, R" rl="R" position="P" status="D60" team_abbrev="TOR" team_id="141" parent_team_abbrev="TOR" parent_team_id="141" avg=".000" hr="0" rbi="0" wins="1" losses="2" era="6.04"/>
		<player id="448722" first="Juan" last="Perez" num="57" boxname="Perez, J" rl="L" position="P" status="D60" team_abbrev="TOR" team_id="141" parent_team_abbrev="TOR" parent_team_id="141" avg=".000" hr="0" rbi="0" wins="1" losses="2" era="3.69"/>
<coach position="manager" first="John" last="Gibbons" id="114744" num="5"/><coach position="hitting_coach" first="Chad" last="Mottola" id="119456" num="39"/><coach position="pitching_coach" first="Pete" last="Walker" id="123839" num="40"/><coach position="first_base_coach" first="Dwayne" last="Murphy" id="119551" num="25"/><coach position="third_base_coach" first="Luis" last="Rivera" id="121248" num="2"/><coach position="bench_coach" first="DeMarlo" last="Hale" id="427204" num="20"/><coach position="bullpen_coach" first="Pat" last="Hentgen" id="115797" num="41"/><coach position="bullpen_catcher" first="Alex" last="Andreopoulos" id="432938" num="61"/>	</team>
	<team type="home" id="BAL" name="Baltimore Orioles">
		<player id="506988" first="Mike" last="Belfiore" num="65" boxname="Belfiore" rl="L" position="P" status="A" team_abbrev="BAL" team_id="110" parent_team_abbrev="BAL" parent_team_id="110" avg=".000" hr="0" rbi="0" wins="0" losses="0" era="-"/>
		<player id="502154" first="Zach" last="Britton" num="53" boxname="Britton" rl="L" position="P" status="A" team_abbrev="BAL" team_id="110" parent_team_abbrev="BAL" parent_team_id="110" avg=".000" hr="0" rbi="0" wins="2" losses="3" era="5.45"/>
		<player id="458210" first="Alexi" last="Casilla" num="12" boxname="Casilla, A" rl="R" position="2B" status="A" team_abbrev="BAL" team_id="110" parent_team_abbrev="BAL" parent_team_id="110" avg=".214" hr="1" rbi="10"/>
		<player id="612672" first="Wei-Yin" last="Chen" num="16" boxname="Chen, W" rl="L" position="P" status="A" team_abbrev="BAL" team_id="110" parent_team_abbrev="BAL" parent_team_id="110" avg=".000" hr="0" rbi="0" wins="7" losses="7" era="4.03"/>
		<player id="502182" first="Steve" last="Clevenger" num="45" boxname="Clevenger" rl="R" position="C" status="A" team_abbrev="BAL" team_id="110" parent_team_abbrev="BAL" parent_team_id="110" avg=".211" hr="0" rbi="2"/>
		<player id="448801" first="Chris" last="Davis" num="19" boxname="Davis, C" rl="R" position="1B" status="A" team_abbrev="BAL" team_id="110" parent_team_abbrev="BAL" parent_team_id="110" avg=".285" hr="52" rbi="137"/>
		<player id="447736" first="Chris" last="Dickerson" num="36" boxname="Dickerson" rl="L" position="LF" status="A" team_abbrev="BAL" team_id="110" parent_team_abbrev="BAL" parent_team_id="110" avg=".238" hr="4" rbi="13"/>
		<player id="444857" first="Scott" last="Feldman" num="34" boxname="Feldman" rl="R" position="P" status="A" team_abbrev="BAL" team_id="110" parent_team_abbrev="BAL" parent_team_id="110" avg=".162" hr="1" rbi="8" wins="12" losses="11" era="3.51"/>
		<player id="475247" first="Ryan" last="Flaherty" num="3" boxname="Flaherty" rl="R" position="2B" current_position="1B" status="A" team_abbrev="BAL" team_id="110" parent_team_abbrev="BAL" parent_team_id="110" avg=".218" hr="10" rbi="25"/>
		<player id="592332" first="Kevin" last="Gausman" num="37" boxname="Gausman" rl="R" position="P" status="A" team_abbrev="BAL" team_id="110" parent_team_abbrev="BAL" parent_team_id="110" avg=".000" hr="0" rbi="0" wins="2" losses="5" era="5.83"/>
		<player id="456068" first="Miguel" last="Gonzalez" num="50" boxname="Gonzalez, M" rl="R" position="P" current_position="P" status="A" team_abbrev="BAL" team_id="110" parent_team_abbrev="BAL" parent_team_id="110" bat_order="0" game_position="P" avg=".000" hr="0" rbi="0" wins="10" losses="8" era="3.94"/>
		<player id="434628" first="Jason" last="Hammel" num="39" boxname="Hammel" rl="R" position="P" status="A" team_abbrev="BAL" team_id="110" parent_team_abbrev="BAL" parent_team_id="110" avg=".000" hr="0" rbi="0" wins="7" losses="8" era="5.05"/>
		<player id="429666" first="J.J." last="Hardy" num="2" boxname="Hardy" rl="R" position="SS" current_position="SS" status="A" team_abbrev="BAL" team_id="110" parent_team_abbrev="BAL" parent_team_id="110" bat_order="6" game_position="SS" avg=".263" hr="25" rbi="74"/>
		<player id="488984" first="Tommy" last="Hunter" num="29" boxname="Hunter, T" rl="R" position="P" current_position="P" status="A" team_abbrev="BAL" team_id="110" parent_team_abbrev="BAL" parent_team_id="110" avg=".000" hr="0" rbi="0" wins="6" losses="5" era="2.74"/>
		<player id="430681" first="Dan" last="Johnson" num="55" boxname="Johnson, D" rl="R" position="1B" status="A" team_abbrev="BAL" team_id="110" parent_team_abbrev="BAL" parent_team_id="110" avg=".000" hr="0" rbi="0"/>
		<player id="462382" first="Jim" last="Johnson" num="43" boxname="Johnson, J" rl="R" position="P" current_position="P" status="A" team_abbrev="BAL" team_id="110" parent_team_abbrev="BAL" parent_team_id="110" avg=".000" hr="0" rbi="0" wins="3" losses="8" era="2.94"/>
		<player id="489002" first="Steve" last="Johnson" num="52" boxname="Johnson, S" rl="R" position="P" status="A" team_abbrev="BAL" team_id="110" parent_team_abbrev="BAL" parent_team_id="110" avg=".000" hr="0" rbi="0" wins="1" losses="1" era="7.07"/>
		<player id="430945" first="Adam" last="Jones" num="10" boxname="Jones, Ad" rl="R" position="CF" current_position="CF" status="A" team_abbrev="BAL" team_id="110" parent_team_abbrev="BAL" parent_team_id="110" bat_order="4" game_position="CF" avg=".285" hr="32" rbi="106"/>
		<player id="455976" first="Nick" last="Markakis" num="21" boxname="Markakis" rl="L" position="RF" current_position="RF" status="A" team_abbrev="BAL" team_id="110" parent_team_abbrev="BAL" parent_team_id="110" bat_order="2" game_position="RF" avg=".269" hr="10" rbi="58"/>
		<player id="451085" first="Brian" last="Matusz" num="17" boxname="Matusz" rl="L" position="P" status="A" team_abbrev="BAL" team_id="110" parent_team_abbrev="BAL" parent_team_id="110" avg=".000" hr="0" rbi="0" wins="2" losses="1" era="3.55"/>
		<player id="519008" first="T.J." last="McFarland" num="66" boxname="McFarland" rl="L" position="P" status="A" team_abbrev="BAL" team_id="110" parent_team_abbrev="BAL" parent_team_id="110" avg=".000" hr="0" rbi="0" wins="3" losses="1" era="4.28"/>
		<player id="434661" first="Nate" last="McLouth" num="9" boxname="McLouth" rl="R" position="LF" status="A" team_abbrev="BAL" team_id="110" parent_team_abbrev="BAL" parent_team_id="110" avg=".260" hr="12" rbi="34"/>
		<player id="434604" first="Michael" last="Morse" num="38" boxname="Morse" rl="R" position="LF" status="A" team_abbrev="BAL" team_id="110" parent_team_abbrev="BAL" parent_team_id="110" avg=".215" hr="13" rbi="27"/>
		<player id="502032" first="Bud" last="Norris" num="25" boxname="Norris, B" rl="R" position="P" status="A" team_abbrev="BAL" team_id="110" parent_team_abbrev="BAL" parent_team_id="110" avg=".429" hr="0" rbi="0" wins="10" losses="12" era="4.18"/>
		<player id="503285" first="Darren" last="O'Day" num="56" boxname="O'Day" rl="R" position="P" status="A" team_abbrev="BAL" team_id="110" parent_team_abbrev="BAL" parent_team_id="110" avg=".000" hr="0" rbi="0" wins="5" losses="3" era="2.18"/>
		<player id="461856" first="Troy" last="Patton" num="40" boxname="Patton" rl="L" position="P" status="A" team_abbrev="BAL" team_id="110" parent_team_abbrev="BAL" parent_team_id="110" avg=".000" hr="0" rbi="0" wins="2" losses="0" era="3.70"/>
		<player id="456665" first="Steve" last="Pearce" num="28" boxname="Pearce" rl="R" position="LF" current_position="1B" status="A" team_abbrev="BAL" team_id="110" parent_team_abbrev="BAL" parent_team_id="110" bat_order="7" game_position="1B" avg=".252" hr="4" rbi="10"/>
		<player id="445095" first="Jason" last="Pridie" num="24" boxname="Pridie" rl="R" position="CF" current_position="LF" status="A" team_abbrev="BAL" team_id="110" parent_team_abbrev="BAL" parent_team_id="110" bat_order="8" game_position="LF" avg=".250" hr="0" rbi="1"/>
		<player id="406878" first="Brian" last="Roberts" num="1" boxname="Roberts, B" rl="R" position="2B" current_position="DH" status="A" team_abbrev="BAL" team_id="110" parent_team_abbrev="BAL" parent_team_id="110" bat_order="1" game_position="DH" avg=".242" hr="7" rbi="38"/>
		<player id="408061" first="Francisco" last="Rodriguez" num="57" boxname="Rodriguez, Fr" rl="R" position="P" status="A" team_abbrev="BAL" team_id="110" parent_team_abbrev="BAL" parent_team_id="110" avg=".000" hr="0" rbi="0" wins="3" losses="2" era="2.70"/>
		<player id="570731" first="Jonathan" last="Schoop" num="6" boxname="Schoop" rl="R" position="3B" current_position="2B" status="A" team_abbrev="BAL" team_id="110" parent_team_abbrev="BAL" parent_team_id="110" bat_order="9" game_position="2B" avg=".667" hr="1" rbi="1"/>
		<player id="430965" first="Chris" last="Snyder" num="48" boxname="Snyder, C" rl="R" position="C" status="A" team_abbrev="BAL" team_id="110" parent_team_abbrev="BAL" parent_team_id="110" avg=".105" hr="0" rbi="1"/>
		<player id="502139" first="Josh" last="Stinson" num="60" boxname="Stinson" rl="R" position="P" status="A" team_abbrev="BAL" team_id="110" parent_team_abbrev="BAL" parent_team_id="110" avg=".000" hr="0" rbi="0" wins="0" losses="0" era="2.81"/>
		<player id="501957" first="Chris" last="Tillman" num="30" boxname="Tillman" rl="R" position="P" status="A" team_abbrev="BAL" team_id="110" parent_team_abbrev="BAL" parent_team_id="110" avg=".000" hr="0" rbi="0" wins="16" losses="7" era="3.62"/>
		<player id="625329" first="Henry" last="Urrutia" num="51" boxname="Urrutia" rl="R" position="LF" status="A" team_abbrev="BAL" team_id="110" parent_team_abbrev="BAL" parent_team_id="110" avg=".276" hr="0" rbi="2"/>
		<player id="502143" first="Danny" last="Valencia" num="35" boxname="Valencia, D" rl="R" position="3B" current_position="3B" status="A" team_abbrev="BAL" team_id="110" parent_team_abbrev="BAL" parent_team_id="110" bat_order="3" game_position="3B" avg=".297" hr="8" rbi="22"/>
		<player id="446308" first="Matt" last="Wieters" num="32" boxname="Wieters" rl="R" position="C" current_position="C" status="A" team_abbrev="BAL" team_id="110" parent_team_abbrev="BAL" parent_team_id="110" bat_order="5" game_position="C" avg=".233" hr="21" rbi="76"/>
		<player id="542919" first="Eric" last="Beaulac" num="" boxname="Beaulac" rl="R" position="P" status="D15" team_abbrev="BAL" team_id="110" parent_team_abbrev="BAL" parent_team_id="110" avg=".000" hr="0" rbi="0" wins="0" losses="0" era="-"/>
		<player id="592518" first="Manny" last="Machado" num="13" boxname="Machado, M" rl="R" position="3B" status="D60" team_abbrev="BAL" team_id="110" parent_team_abbrev="BAL" parent_team_id="110" avg=".283" hr="14" rbi="71"/>
		<player id="460099" first="Nolan" last="Reimold" num="14" boxname="Reimold" rl="R" position="LF" status="D60" team_abbrev="BAL" team_id="110" parent_team_abbrev="BAL" parent_team_id="110" avg=".195" hr="5" rbi="12"/>
<coach position="manager" first="Buck" last="Showalter" id="427469" num="26"/><coach position="batting_coach" first="Jim" last="Presley" id="120755" num="15"/><coach position="assistant_hitting_coach" first="Einar" last="Diaz" id="113330" num=""/><coach position="pitching_coach" first="Rick" last="Adair" id="547748" num="41"/><coach position="pitching_coach" first="Bill" last="Castro" id="112130" num=""/><coach position="first_base_coach" first="Wayne" last="Kirby" id="117114" num="23"/><coach position="third_base_coach" first="Bobby" last="Dickerson" id="433638" num="11"/><coach position="bench_coach" first="John" last="Russell" id="121571" num="77"/><coach position="bullpen_coach" first="Scott" last="McGregor" id="118728" num=""/><coach position="bullpen_catcher" first="Rudy" last="Arias" id="608791" num="62"/>	</team>
<umpires><umpire position="home" name="Gerry Davis" id="427103"/><umpire position="first" name="Tom Hallion" id="427206"/><umpire position="second" name="Ron Kulpa" id="427292"/><umpire position="third" name="Chris Guccione" id="427197"/></umpires></game>