<!--Copyright 2013 MLB Advanced Media, L.P.  Use of any content on this page acknowledges agreement to the terms posted here http://gdx.mlb.com/components/copyright.txt--><game venue="Safeco Field" date="August 6, 2013">
	<team type="away" id="TOR" name="Toronto Blue Jays">
		<player id="450317" first="J.P." last="Arencibia" num="9" boxname="Arencibia" rl="R" position="C" status="A" team_abbrev="TOR" team_id="141" parent_team_abbrev="TOR" parent_team_id="141" avg=".211" hr="17" rbi="45"/>
		<player id="430832" first="Jose" last="Bautista" num="19" boxname="Bautista" rl="R" position="RF" current_position="RF" status="A" team_abbrev="TOR" team_id="141" parent_team_abbrev="TOR" parent_team_id="141" bat_order="3" game_position="RF" avg=".257" hr="25" rbi="68"/>
		<player id="466988" first="Emilio" last="Bonifacio" num="1" boxname="Bonifacio" rl="R" position="2B" current_position="LF" status="A" team_abbrev="TOR" team_id="141" parent_team_abbrev="TOR" parent_team_id="141" bat_order="9" game_position="LF" avg=".216" hr="3" rbi="16"/>
		<player id="279824" first="Mark" last="Buehrle" num="56" boxname="Buehrle" rl="L" position="P" status="A" team_abbrev="TOR" team_id="141" parent_team_abbrev="TOR" parent_team_id="141" avg=".000" hr="0" rbi="0" wins="7" losses="7" era="4.41"/>
		<player id="446399" first="Brett" last="Cecil" num="27" boxname="Cecil" rl="L" position="P" current_position="P" status="A" team_abbrev="TOR" team_id="141" parent_team_abbrev="TOR" parent_team_id="141" avg=".000" hr="0" rbi="0" wins="5" losses="1" era="2.77"/>
		<player id="434658" first="Rajai" last="Davis" num="11" boxname="Davis, R" rl="R" position="RF" status="A" team_abbrev="TOR" team_id="141" parent_team_abbrev="TOR" parent_team_id="141" avg=".279" hr="2" rbi="12"/>
		<player id="136660" first="Mark" last="DeRosa" num="16" boxname="DeRosa" rl="R" position="3B" status="A" team_abbrev="TOR" team_id="141" parent_team_abbrev="TOR" parent_team_id="141" avg=".231" hr="7" rbi="29"/>
		<player id="285079" first="R.A." last="Dickey" num="43" boxname="Dickey" rl="R" position="P" status="A" team_abbrev="TOR" team_id="141" parent_team_abbrev="TOR" parent_team_id="141" avg=".333" hr="0" rbi="1" wins="9" losses="11" era="4.49"/>
		<player id="429665" first="Edwin" last="Encarnacion" num="10" boxname="Encarnacion" rl="R" position="1B" current_position="DH" status="A" team_abbrev="TOR" team_id="141" parent_team_abbrev="TOR" parent_team_id="141" bat_order="4" game_position="DH" avg=".281" hr="29" rbi="88"/>
		<player id="457918" first="J.A." last="Happ" num="48" boxname="Happ" rl="L" position="P" status="A" team_abbrev="TOR" team_id="141" parent_team_abbrev="TOR" parent_team_id="141" avg=".000" hr="0" rbi="0" wins="2" losses="2" era="4.91"/>
		<player id="430895" first="Maicer" last="Izturis" num="3" boxname="Izturis, M" rl="R" position="3B" current_position="2B" status="A" team_abbrev="TOR" team_id="141" parent_team_abbrev="TOR" parent_team_id="141" bat_order="2" game_position="2B" avg=".238" hr="5" rbi="30"/>
		<player id="445163" first="Casey" last="Janssen" num="44" boxname="Janssen" rl="R" position="P" status="A" team_abbrev="TOR" team_id="141" parent_team_abbrev="TOR" parent_team_id="141" avg=".000" hr="0" rbi="0" wins="4" losses="0" era="2.23"/>
		<player id="435178" first="Josh" last="Johnson" num="55" boxname="Johnson, Jo" rl="R" position="P" current_position="P" status="A" team_abbrev="TOR" team_id="141" parent_team_abbrev="TOR" parent_team_id="141" bat_order="0" game_position="P" avg=".000" hr="0" rbi="0" wins="1" losses="8" era="6.60"/>
		<player id="543434" first="Brett" last="Lawrie" num="13" boxname="Lawrie" rl="R" position="3B" current_position="3B" status="A" team_abbrev="TOR" team_id="141" parent_team_abbrev="TOR" parent_team_id="141" bat_order="7" game_position="3B" avg=".233" hr="9" rbi="24"/>
		<player id="453184" first="Brad" last="Lincoln" num="49" boxname="Lincoln" rl="R" position="P" status="A" team_abbrev="TOR" team_id="141" parent_team_abbrev="TOR" parent_team_id="141" avg=".000" hr="0" rbi="0" wins="0" losses="1" era="3.65"/>
		<player id="452252" first="Adam" last="Lind" num="26" boxname="Lind" rl="L" position="1B" current_position="1B" status="A" team_abbrev="TOR" team_id="141" parent_team_abbrev="TOR" parent_team_id="141" bat_order="5" game_position="1B" avg=".278" hr="13" rbi="40"/>
		<player id="571901" first="Aaron" last="Loup" num="62" boxname="Loup" rl="L" position="P" status="A" team_abbrev="TOR" team_id="141" parent_team_abbrev="TOR" parent_team_id="141" avg=".000" hr="0" rbi="0" wins="4" losses="3" era="1.93"/>
		<player id="119984" first="Darren" last="Oliver" num="38" boxname="Oliver, D" rl="L" position="P" status="A" team_abbrev="TOR" team_id="141" parent_team_abbrev="TOR" parent_team_id="141" avg=".000" hr="0" rbi="0" wins="3" losses="2" era="3.60"/>
		<player id="448722" first="Juan" last="Perez" num="57" boxname="Perez, J" rl="L" position="P" current_position="P" status="A" team_abbrev="TOR" team_id="141" parent_team_abbrev="TOR" parent_team_id="141" avg=".000" hr="0" rbi="0" wins="1" losses="2" era="1.93"/>
		<player id="458675" first="Colby" last="Rasmus" num="28" boxname="Rasmus, C" rl="L" position="CF" current_position="CF" status="A" team_abbrev="TOR" team_id="141" parent_team_abbrev="TOR" parent_team_id="141" bat_order="6" game_position="CF" avg=".276" hr="17" rbi="56"/>
		<player id="408314" first="Jose" last="Reyes" num="7" boxname="Reyes" rl="R" position="SS" current_position="SS" status="A" team_abbrev="TOR" team_id="141" parent_team_abbrev="TOR" parent_team_id="141" bat_order="1" game_position="SS" avg=".314" hr="7" rbi="22"/>
		<player id="469134" first="Esmil" last="Rogers" num="32" boxname="Rogers, E" rl="R" position="P" status="A" team_abbrev="TOR" team_id="141" parent_team_abbrev="TOR" parent_team_id="141" avg=".000" hr="0" rbi="0" wins="3" losses="6" era="4.61"/>
		<player id="435045" first="Sergio" last="Santos" num="21" boxname="Santos, S" rl="R" position="P" current_position="P" status="A" team_abbrev="TOR" team_id="141" parent_team_abbrev="TOR" parent_team_id="141" avg=".000" hr="0" rbi="0" wins="0" losses="1" era="2.84"/>
		<player id="489365" first="Josh" last="Thole" num="30" boxname="Thole" rl="R" position="C" current_position="C" status="A" team_abbrev="TOR" team_id="141" parent_team_abbrev="TOR" parent_team_id="141" bat_order="8" game_position="C" avg=".105" hr="0" rbi="3"/>
		<player id="474599" first="Neil" last="Wagner" num="45" boxname="Wagner" rl="R" position="P" status="A" team_abbrev="TOR" team_id="141" parent_team_abbrev="TOR" parent_team_id="141" avg=".000" hr="0" rbi="0" wins="2" losses="3" era="2.91"/>
		<player id="466320" first="Melky" last="Cabrera" num="53" boxname="Cabrera, Me" rl="L" position="LF" status="D15" team_abbrev="TOR" team_id="141" parent_team_abbrev="TOR" parent_team_id="141" avg=".279" hr="3" rbi="30"/>
		<player id="447755" first="Steve" last="Delabar" num="50" boxname="Delabar" rl="R" position="P" status="D15" team_abbrev="TOR" team_id="141" parent_team_abbrev="TOR" parent_team_id="141" avg=".000" hr="0" rbi="0" wins="5" losses="2" era="2.90"/>
		<player id="430661" first="Dustin" last="McGowan" num="29" boxname="McGowan" rl="R" position="P" status="D15" team_abbrev="TOR" team_id="141" parent_team_abbrev="TOR" parent_team_id="141" avg=".000" hr="0" rbi="0" wins="0" losses="0" era="2.12"/>
		<player id="571800" first="Drew" last="Hutchison" num="36" boxname="Hutchison" rl="R" position="P" status="D60" team_abbrev="TOR" team_id="141" parent_team_abbrev="TOR" parent_team_id="141" avg=".000" hr="0" rbi="0" wins="0" losses="0" era="-"/>
		<player id="453344" first="Brandon" last="Morrow" num="23" boxname="Morrow" rl="R" position="P" status="D60" team_abbrev="TOR" team_id="141" parent_team_abbrev="TOR" parent_team_id="141" avg=".000" hr="0" rbi="0" wins="2" losses="3" era="5.63"/>
		<player id="150009" first="Ramon" last="Ortiz" num="34" boxname="Ortiz, R" rl="R" position="P" status="D60" team_abbrev="TOR" team_id="141" parent_team_abbrev="TOR" parent_team_id="141" avg=".000" hr="0" rbi="0" wins="1" losses="2" era="6.04"/>
		<player id="469802" first="Luis" last="Perez" num="47" boxname="Perez, L" rl="L" position="P" status="D60" team_abbrev="TOR" team_id="141" parent_team_abbrev="TOR" parent_team_id="141" avg=".000" hr="0" rbi="0" wins="0" losses="0" era="-"/>
<coach position="manager" first="John" last="Gibbons" id="114744" num="5"/><coach position="hitting_coach" first="Chad" last="Mottola" id="119456" num="39"/><coach position="pitching_coach" first="Pete" last="Walker" id="123839" num="40"/><coach position="first_base_coach" first="Dwayne" last="Murphy" id="119551" num="25"/><coach position="third_base_coach" first="Luis" last="Rivera" id="121248" num="2"/><coach position="bench_coach" first="DeMarlo" last="Hale" id="427204" num="20"/><coach position="bullpen_coach" first="Pat" last="Hentgen" id="115797" num="41"/><coach position="bullpen_catcher" first="Alex" last="Andreopoulos" id="432938" num="61"/>	</team>
	<team type="home" id="SEA" name="Seattle Mariners">
		<player id="554429" first="Dustin" last="Ackley" num="13" boxname="Ackley" rl="R" position="2B" status="A" team_abbrev="SEA" team_id="136" parent_team_abbrev="SEA" parent_team_id="136" avg=".213" hr="1" rbi="17"/>
		<player id="111072" first="Henry" last="Blanco" num="33" boxname="Blanco, H" rl="R" position="C" current_position="C" status="A" team_abbrev="SEA" team_id="136" parent_team_abbrev="SEA" parent_team_id="136" bat_order="9" game_position="C" avg=".182" hr="3" rbi="14"/>
		<player id="605169" first="Carter" last="Capps" num="58" boxname="Capps" rl="R" position="P" current_position="P" status="A" team_abbrev="SEA" team_id="136" parent_team_abbrev="SEA" parent_team_id="136" avg=".000" hr="0" rbi="0" wins="2" losses="2" era="6.37"/>
		<player id="346795" first="Endy" last="Chavez" num="9" boxname="Chavez, En" rl="L" position="CF" status="A" team_abbrev="SEA" team_id="136" parent_team_abbrev="SEA" parent_team_id="136" avg=".273" hr="2" rbi="13"/>
		<player id="543144" first="Danny" last="Farquhar" num="40" boxname="Farquhar" rl="R" position="P" status="A" team_abbrev="SEA" team_id="136" parent_team_abbrev="SEA" parent_team_id="136" avg=".000" hr="0" rbi="0" wins="0" losses="0" era="5.09"/>
		<player id="545338" first="Nick" last="Franklin" num="20" boxname="Franklin" rl="R" position="2B" current_position="2B" status="A" team_abbrev="SEA" team_id="136" parent_team_abbrev="SEA" parent_team_id="136" bat_order="2" game_position="2B" avg=".250" hr="10" rbi="32"/>
		<player id="518703" first="Charlie" last="Furbush" num="41" boxname="Furbush" rl="L" position="P" status="A" team_abbrev="SEA" team_id="136" parent_team_abbrev="SEA" parent_team_id="136" avg=".000" hr="0" rbi="0" wins="2" losses="4" era="3.35"/>
		<player id="421685" first="Aaron" last="Harang" num="39" boxname="Harang" rl="R" position="P" status="A" team_abbrev="SEA" team_id="136" parent_team_abbrev="SEA" parent_team_id="136" avg=".000" hr="0" rbi="0" wins="5" losses="10" era="5.27"/>
		<player id="433587" first="Felix" last="Hernandez" num="34" boxname="Hernandez, F" rl="R" position="P" current_position="P" status="A" team_abbrev="SEA" team_id="136" parent_team_abbrev="SEA" parent_team_id="136" bat_order="0" game_position="P" avg=".000" hr="0" rbi="0" wins="11" losses="4" era="2.30"/>
		<player id="116380" first="Raul" last="Ibanez" num="28" boxname="Ibanez" rl="R" position="LF" current_position="LF" status="A" team_abbrev="SEA" team_id="136" parent_team_abbrev="SEA" parent_team_id="136" bat_order="5" game_position="LF" avg=".251" hr="24" rbi="58"/>
		<player id="547874" first="Hisashi" last="Iwakuma" num="18" boxname="Iwakuma" rl="R" position="P" status="A" team_abbrev="SEA" team_id="136" parent_team_abbrev="SEA" parent_team_id="136" avg=".000" hr="0" rbi="0" wins="10" losses="5" era="2.75"/>
		<player id="476595" first="Lucas" last="Luetge" num="44" boxname="Luetge" rl="L" position="P" current_position="P" status="A" team_abbrev="SEA" team_id="136" parent_team_abbrev="SEA" parent_team_id="136" avg=".000" hr="0" rbi="0" wins="0" losses="2" era="4.95"/>
		<player id="543506" first="Brandon" last="Maurer" num="37" boxname="Maurer" rl="R" position="P" status="A" team_abbrev="SEA" team_id="136" parent_team_abbrev="SEA" parent_team_id="136" avg=".000" hr="0" rbi="0" wins="2" losses="7" era="7.16"/>
		<player id="500721" first="Yoervis" last="Medina" num="31" boxname="Medina" rl="R" position="P" status="A" team_abbrev="SEA" team_id="136" parent_team_abbrev="SEA" parent_team_id="136" avg=".000" hr="0" rbi="0" wins="3" losses="3" era="2.84"/>
		<player id="543543" first="Brad" last="Miller" num="5" boxname="Miller, B" rl="R" position="SS" current_position="SS" status="A" team_abbrev="SEA" team_id="136" parent_team_abbrev="SEA" parent_team_id="136" bat_order="1" game_position="SS" avg=".244" hr="2" rbi="16"/>
		<player id="434778" first="Kendrys" last="Morales" num="8" boxname="Morales, K" rl="R" position="1B" current_position="DH" status="A" team_abbrev="SEA" team_id="136" parent_team_abbrev="SEA" parent_team_id="136" bat_order="4" game_position="DH" avg=".296" hr="17" rbi="63"/>
		<player id="434604" first="Michael" last="Morse" num="38" boxname="Morse" rl="R" position="LF" current_position="RF" status="A" team_abbrev="SEA" team_id="136" parent_team_abbrev="SEA" parent_team_id="136" bat_order="6" game_position="RF" avg=".245" hr="12" rbi="26"/>
		<player id="424144" first="Oliver" last="Perez" num="59" boxname="Perez, O" rl="L" position="P" status="A" team_abbrev="SEA" team_id="136" parent_team_abbrev="SEA" parent_team_id="136" avg=".000" hr="0" rbi="0" wins="2" losses="3" era="3.12"/>
		<player id="279827" first="Humberto" last="Quintero" num="35" boxname="Quintero" rl="R" position="C" status="A" team_abbrev="SEA" team_id="136" parent_team_abbrev="SEA" parent_team_id="136" avg=".280" hr="3" rbi="10"/>
		<player id="541640" first="Erasmo" last="Ramirez" num="50" boxname="Ramirez, Er" rl="R" position="P" status="A" team_abbrev="SEA" team_id="136" parent_team_abbrev="SEA" parent_team_id="136" avg=".000" hr="0" rbi="0" wins="3" losses="0" era="7.25"/>
		<player id="453895" first="Brendan" last="Ryan" num="26" boxname="Ryan" rl="R" position="SS" status="A" team_abbrev="SEA" team_id="136" parent_team_abbrev="SEA" parent_team_id="136" avg=".188" hr="3" rbi="17"/>
		<player id="434578" first="Joe" last="Saunders" num="23" boxname="Saunders, J" rl="L" position="P" status="A" team_abbrev="SEA" team_id="136" parent_team_abbrev="SEA" parent_team_id="136" avg=".000" hr="0" rbi="0" wins="10" losses="10" era="4.58"/>
		<player id="459431" first="Michael" last="Saunders" num="55" boxname="Saunders, M" rl="R" position="RF" current_position="CF" status="A" team_abbrev="SEA" team_id="136" parent_team_abbrev="SEA" parent_team_id="136" bat_order="8" game_position="CF" avg=".232" hr="10" rbi="37"/>
		<player id="572122" first="Kyle" last="Seager" num="15" boxname="Seager" rl="R" position="3B" current_position="3B" status="A" team_abbrev="SEA" team_id="136" parent_team_abbrev="SEA" parent_team_id="136" bat_order="3" game_position="3B" avg=".295" hr="17" rbi="51"/>
		<player id="475253" first="Justin" last="Smoak" num="17" boxname="Smoak" rl="L" position="1B" current_position="1B" status="A" team_abbrev="SEA" team_id="136" parent_team_abbrev="SEA" parent_team_id="136" bat_order="7" game_position="1B" avg=".273" hr="11" rbi="26"/>
		<player id="429711" first="Franklin" last="Gutierrez" num="21" boxname="Gutierrez, F" rl="R" position="CF" status="D15" team_abbrev="SEA" team_id="136" parent_team_abbrev="SEA" parent_team_id="136" avg=".267" hr="5" rbi="11"/>
		<player id="491696" first="Jesus" last="Sucre" num="2" boxname="Sucre" rl="R" position="C" status="D15" team_abbrev="SEA" team_id="136" parent_team_abbrev="SEA" parent_team_id="136" avg=".192" hr="0" rbi="3"/>
		<player id="572287" first="Mike" last="Zunino" num="3" boxname="Zunino" rl="R" position="C" status="D15" team_abbrev="SEA" team_id="136" parent_team_abbrev="SEA" parent_team_id="136" avg=".242" hr="2" rbi="10"/>
		<player id="543668" first="Stephen" last="Pryor" num="46" boxname="Pryor" rl="R" position="P" status="D60" team_abbrev="SEA" team_id="136" parent_team_abbrev="SEA" parent_team_id="136" avg=".000" hr="0" rbi="0" wins="0" losses="0" era="0.00"/>
<coach position="manager" first="Eric" last="Wedge" id="124029" num="22"/><coach position="batting_coach" first="Dave" last="Hansen" id="115436" num="25"/><coach position="pitching_coach" first="Carl" last="Willis" id="124356" num="48"/><coach position="first_base_coach" first="Mike" last="Brumley" id="111624" num="29"/><coach position="third_base_coach" first="Jeff" last="Datz" id="113066" num="43"/><coach position="bench_coach" first="Robby" last="Thompson" id="123300" num="6"/><coach position="bullpen_coach" first="Jaime" last="Navarro" id="119667" num="47"/><coach position="bullpen_catcher" first="Jason" last="Phillips" id="282993" num="62"/><coach position="coach" first="Daren" last="Brown" id="492474" num="52"/>	</team>
<umpires><umpire position="home" name="Quinn Wolcott" id="511890"/><umpire position="first" name="Dale Scott" id="427457"/><umpire position="second" name="Todd Tichenor" id="429805"/><umpire position="third" name="CB Bucknor" id="427044"/></umpires></game>