<!--Copyright 2013 MLB Advanced Media, L.P.  Use of any content on this page acknowledges agreement to the terms posted here http://gdx.mlb.com/components/copyright.txt--><game venue="U.S. Cellular Field" date="September 23, 2013">
	<team type="away" id="TOR" name="Toronto Blue Jays">
		<player id="119984" first="Darren" last="Oliver" num="38" boxname="Oliver, D" rl="L" position="P" status="A" team_abbrev="TOR" team_id="141" parent_team_abbrev="TOR" parent_team_id="141" avg=".000" hr="0" rbi="0" wins="3" losses="4" era="3.94"/>
		<player id="136660" first="Mark" last="DeRosa" num="16" boxname="DeRosa" rl="R" position="3B" current_position="2B" status="A" team_abbrev="TOR" team_id="141" parent_team_abbrev="TOR" parent_team_id="141" bat_order="5" game_position="1B" avg=".229" hr="7" rbi="32"/>
		<player id="150009" first="Ramon" last="Ortiz" num="34" boxname="Ortiz, R" rl="R" position="P" status="A" team_abbrev="TOR" team_id="141" parent_team_abbrev="TOR" parent_team_id="141" avg=".000" hr="0" rbi="0" wins="1" losses="2" era="6.04"/>
		<player id="279824" first="Mark" last="Buehrle" num="56" boxname="Buehrle" rl="L" position="P" status="A" team_abbrev="TOR" team_id="141" parent_team_abbrev="TOR" parent_team_id="141" avg=".000" hr="0" rbi="0" wins="12" losses="9" era="4.09"/>
		<player id="285079" first="R.A." last="Dickey" num="43" boxname="Dickey" rl="R" position="P" status="A" team_abbrev="TOR" team_id="141" parent_team_abbrev="TOR" parent_team_id="141" avg=".333" hr="0" rbi="1" wins="13" losses="13" era="4.27"/>
		<player id="408314" first="Jose" last="Reyes" num="7" boxname="Reyes" rl="R" position="SS" status="A" team_abbrev="TOR" team_id="141" parent_team_abbrev="TOR" parent_team_id="141" avg=".292" hr="10" rbi="35"/>
		<player id="429665" first="Edwin" last="Encarnacion" num="10" boxname="Encarnacion" rl="R" position="1B" status="A" team_abbrev="TOR" team_id="141" parent_team_abbrev="TOR" parent_team_id="141" avg=".272" hr="36" rbi="104"/>
		<player id="430661" first="Dustin" last="McGowan" num="29" boxname="McGowan" rl="R" position="P" status="A" team_abbrev="TOR" team_id="141" parent_team_abbrev="TOR" parent_team_id="141" avg=".000" hr="0" rbi="0" wins="0" losses="0" era="2.31"/>
		<player id="430832" first="Jose" last="Bautista" num="19" boxname="Bautista" rl="R" position="RF" status="A" team_abbrev="TOR" team_id="141" parent_team_abbrev="TOR" parent_team_id="141" avg=".259" hr="28" rbi="73"/>
		<player id="430895" first="Maicer" last="Izturis" num="3" boxname="Izturis, M" rl="R" position="3B" status="A" team_abbrev="TOR" team_id="141" parent_team_abbrev="TOR" parent_team_id="141" avg=".236" hr="5" rbi="32"/>
		<player id="434658" first="Rajai" last="Davis" num="11" boxname="Davis, R" rl="R" position="RF" current_position="RF" status="A" team_abbrev="TOR" team_id="141" parent_team_abbrev="TOR" parent_team_id="141" bat_order="1" game_position="RF" avg=".266" hr="6" rbi="24"/>
		<player id="435045" first="Sergio" last="Santos" num="21" boxname="Santos, S" rl="R" position="P" status="A" team_abbrev="TOR" team_id="141" parent_team_abbrev="TOR" parent_team_id="141" avg=".000" hr="0" rbi="0" wins="0" losses="1" era="1.64"/>
		<player id="435081" first="Mike" last="Nickeas" num="15" boxname="Nickeas" rl="R" position="C" status="A" team_abbrev="TOR" team_id="141" parent_team_abbrev="TOR" parent_team_id="141" avg=".000" hr="0" rbi="0"/>
		<player id="435178" first="Josh" last="Johnson" num="55" boxname="Johnson, Jo" rl="R" position="P" status="A" team_abbrev="TOR" team_id="141" parent_team_abbrev="TOR" parent_team_id="141" avg=".000" hr="0" rbi="0" wins="2" losses="8" era="6.20"/>
		<player id="445163" first="Casey" last="Janssen" num="44" boxname="Janssen" rl="R" position="P" status="A" team_abbrev="TOR" team_id="141" parent_team_abbrev="TOR" parent_team_id="141" avg=".000" hr="0" rbi="0" wins="4" losses="1" era="2.61"/>
		<player id="445170" first="Todd" last="Redmond" num="58" boxname="Redmond" rl="R" position="P" status="A" team_abbrev="TOR" team_id="141" parent_team_abbrev="TOR" parent_team_id="141" avg=".000" hr="0" rbi="0" wins="4" losses="2" era="3.82"/>
		<player id="446399" first="Brett" last="Cecil" num="27" boxname="Cecil" rl="L" position="P" status="A" team_abbrev="TOR" team_id="141" parent_team_abbrev="TOR" parent_team_id="141" avg=".000" hr="0" rbi="0" wins="5" losses="1" era="2.82"/>
		<player id="447755" first="Steve" last="Delabar" num="50" boxname="Delabar" rl="R" position="P" current_position="P" status="A" team_abbrev="TOR" team_id="141" parent_team_abbrev="TOR" parent_team_id="141" avg=".000" hr="0" rbi="0" wins="5" losses="5" era="3.40"/>
		<player id="448722" first="Juan" last="Perez" num="57" boxname="Perez, J" rl="L" position="P" status="A" team_abbrev="TOR" team_id="141" parent_team_abbrev="TOR" parent_team_id="141" avg=".000" hr="0" rbi="0" wins="1" losses="2" era="3.69"/>
		<player id="450317" first="J.P." last="Arencibia" num="9" boxname="Arencibia" rl="R" position="C" current_position="C" status="A" team_abbrev="TOR" team_id="141" parent_team_abbrev="TOR" parent_team_id="141" bat_order="6" game_position="C" avg=".196" hr="20" rbi="53"/>
		<player id="452252" first="Adam" last="Lind" num="26" boxname="Lind" rl="L" position="1B" current_position="1B" status="A" team_abbrev="TOR" team_id="141" parent_team_abbrev="TOR" parent_team_id="141" avg=".283" hr="23" rbi="64"/>
		<player id="453344" first="Brandon" last="Morrow" num="23" boxname="Morrow" rl="R" position="P" status="A" team_abbrev="TOR" team_id="141" parent_team_abbrev="TOR" parent_team_id="141" avg=".000" hr="0" rbi="0" wins="2" losses="3" era="5.63"/>
		<player id="457918" first="J.A." last="Happ" num="48" boxname="Happ" rl="L" position="P" current_position="P" status="A" team_abbrev="TOR" team_id="141" parent_team_abbrev="TOR" parent_team_id="141" bat_order="0" game_position="P" avg=".000" hr="0" rbi="0" wins="4" losses="6" era="4.82"/>
		<player id="458675" first="Colby" last="Rasmus" num="28" boxname="Rasmus, C" rl="L" position="CF" status="A" team_abbrev="TOR" team_id="141" parent_team_abbrev="TOR" parent_team_id="141" avg=".276" hr="22" rbi="66"/>
		<player id="460069" first="Ricky" last="Romero" num="24" boxname="Romero, R" rl="L" position="P" status="A" team_abbrev="TOR" team_id="141" parent_team_abbrev="TOR" parent_team_id="141" avg=".000" hr="0" rbi="0" wins="0" losses="2" era="9.95"/>
		<player id="466320" first="Melky" last="Cabrera" num="53" boxname="Cabrera, Me" rl="L" position="LF" status="A" team_abbrev="TOR" team_id="141" parent_team_abbrev="TOR" parent_team_id="141" avg=".279" hr="3" rbi="30"/>
		<player id="469134" first="Esmil" last="Rogers" num="32" boxname="Rogers, E" rl="R" position="P" status="A" team_abbrev="TOR" team_id="141" parent_team_abbrev="TOR" parent_team_id="141" avg=".000" hr="0" rbi="0" wins="5" losses="8" era="4.52"/>
		<player id="469802" first="Luis" last="Perez" num="47" boxname="Perez, L" rl="L" position="P" status="A" team_abbrev="TOR" team_id="141" parent_team_abbrev="TOR" parent_team_id="141" avg=".000" hr="0" rbi="0" wins="0" losses="1" era="6.00"/>
		<player id="474599" first="Neil" last="Wagner" num="45" boxname="Wagner" rl="R" position="P" status="A" team_abbrev="TOR" team_id="141" parent_team_abbrev="TOR" parent_team_id="141" avg=".000" hr="0" rbi="0" wins="2" losses="4" era="3.75"/>
		<player id="475138" first="Kyle" last="Drabek" num="4" boxname="Drabek" rl="R" position="P" status="A" team_abbrev="TOR" team_id="141" parent_team_abbrev="TOR" parent_team_id="141" avg=".000" hr="0" rbi="0" wins="0" losses="0" era="4.50"/>
		<player id="489365" first="Josh" last="Thole" num="30" boxname="Thole" rl="R" position="C" status="A" team_abbrev="TOR" team_id="141" parent_team_abbrev="TOR" parent_team_id="141" avg=".150" hr="1" rbi="7"/>
		<player id="493128" first="Munenori" last="Kawasaki" num="66" boxname="Kawasaki" rl="R" position="SS" current_position="2B" status="A" team_abbrev="TOR" team_id="141" parent_team_abbrev="TOR" parent_team_id="141" bat_order="2" game_position="2B" avg=".222" hr="1" rbi="24"/>
		<player id="501213" first="Moises" last="Sierra" num="14" boxname="Sierra" rl="R" position="RF" current_position="DH" status="A" team_abbrev="TOR" team_id="141" parent_team_abbrev="TOR" parent_team_id="141" bat_order="4" game_position="DH" avg=".307" hr="1" rbi="11"/>
		<player id="502026" first="Jeremy" last="Jeffress" num="33" boxname="Jeffress" rl="R" position="P" current_position="P" status="A" team_abbrev="TOR" team_id="141" parent_team_abbrev="TOR" parent_team_id="141" avg=".000" hr="0" rbi="0" wins="1" losses="0" era="1.93"/>
		<player id="543238" first="Anthony" last="Gose" num="8" boxname="Gose" rl="L" position="RF" current_position="CF" status="A" team_abbrev="TOR" team_id="141" parent_team_abbrev="TOR" parent_team_id="141" bat_order="9" game_position="CF" avg=".269" hr="2" rbi="9"/>
		<player id="543434" first="Brett" last="Lawrie" num="13" boxname="Lawrie" rl="R" position="3B" current_position="3B" status="A" team_abbrev="TOR" team_id="141" parent_team_abbrev="TOR" parent_team_id="141" bat_order="3" game_position="3B" avg=".255" hr="11" rbi="43"/>
		<player id="554432" first="Chad" last="Jenkins" num="64" boxname="Jenkins" rl="R" position="P" status="A" team_abbrev="TOR" team_id="141" parent_team_abbrev="TOR" parent_team_id="141" avg=".000" hr="0" rbi="0" wins="1" losses="0" era="3.07"/>
		<player id="571901" first="Aaron" last="Loup" num="62" boxname="Loup" rl="L" position="P" status="A" team_abbrev="TOR" team_id="141" parent_team_abbrev="TOR" parent_team_id="141" avg=".000" hr="0" rbi="0" wins="4" losses="6" era="2.51"/>
		<player id="572365" first="Ryan" last="Goins" num="17" boxname="Goins" rl="R" position="SS" current_position="SS" status="A" team_abbrev="TOR" team_id="141" parent_team_abbrev="TOR" parent_team_id="141" bat_order="8" game_position="SS" avg=".233" hr="1" rbi="3"/>
		<player id="607680" first="Kevin" last="Pillar" num="22" boxname="Pillar" rl="R" position="CF" current_position="LF" status="A" team_abbrev="TOR" team_id="141" parent_team_abbrev="TOR" parent_team_id="141" bat_order="7" game_position="LF" avg=".192" hr="2" rbi="10"/>
<coach position="manager" first="John" last="Gibbons" id="114744" num="5"/><coach position="hitting_coach" first="Chad" last="Mottola" id="119456" num="39"/><coach position="pitching_coach" first="Pete" last="Walker" id="123839" num="40"/><coach position="first_base_coach" first="Dwayne" last="Murphy" id="119551" num="25"/><coach position="third_base_coach" first="Luis" last="Rivera" id="121248" num="2"/><coach position="bench_coach" first="DeMarlo" last="Hale" id="427204" num="20"/><coach position="bullpen_coach" first="Pat" last="Hentgen" id="115797" num="41"/><coach position="bullpen_catcher" first="Alex" last="Andreopoulos" id="432938" num="61"/>	</team>
	<team type="home" id="CWS" name="Chicago White Sox">
		<player id="117244" first="Paul" last="Konerko" num="14" boxname="Konerko" rl="R" position="1B" current_position="1B" status="A" team_abbrev="CWS" team_id="145" parent_team_abbrev="CWS" parent_team_id="145" bat_order="4" game_position="1B" avg=".248" hr="11" rbi="53"/>
		<player id="276055" first="Adam" last="Dunn" num="32" boxname="Dunn, A" rl="R" position="1B" status="A" team_abbrev="CWS" team_id="145" parent_team_abbrev="CWS" parent_team_id="145" avg=".218" hr="32" rbi="83"/>
		<player id="425856" first="Gavin" last="Floyd" num="34" boxname="Floyd" rl="R" position="P" status="A" team_abbrev="CWS" team_id="145" parent_team_abbrev="CWS" parent_team_id="145" avg=".000" hr="0" rbi="0" wins="0" losses="4" era="5.18"/>
		<player id="433579" first="John" last="Danks" num="50" boxname="Danks, Jh" rl="L" position="P" status="A" team_abbrev="CWS" team_id="145" parent_team_abbrev="CWS" parent_team_id="145" avg=".000" hr="0" rbi="0" wins="4" losses="14" era="4.75"/>
		<player id="433898" first="Jeff" last="Keppinger" num="7" boxname="Keppinger" rl="R" position="3B" current_position="DH" status="A" team_abbrev="CWS" team_id="145" parent_team_abbrev="CWS" parent_team_id="145" bat_order="3" game_position="DH" avg=".252" hr="4" rbi="40"/>
		<player id="434637" first="Matt" last="Lindstrom" num="27" boxname="Lindstrom" rl="R" position="P" current_position="P" status="A" team_abbrev="CWS" team_id="145" parent_team_abbrev="CWS" parent_team_id="145" avg=".000" hr="0" rbi="0" wins="2" losses="4" era="2.88"/>
		<player id="452095" first="Tyler" last="Flowers" num="21" boxname="Flowers" rl="R" position="C" status="A" team_abbrev="CWS" team_id="145" parent_team_abbrev="CWS" parent_team_id="145" avg=".195" hr="10" rbi="24"/>
		<player id="453264" first="Donnie" last="Veal" num="46" boxname="Veal" rl="L" position="P" current_position="P" status="A" team_abbrev="CWS" team_id="145" parent_team_abbrev="CWS" parent_team_id="145" avg=".000" hr="0" rbi="0" wins="2" losses="3" era="4.82"/>
		<player id="453515" first="David" last="Purcey" num="41" boxname="Purcey" rl="L" position="P" status="A" team_abbrev="CWS" team_id="145" parent_team_abbrev="CWS" parent_team_id="145" avg=".000" hr="0" rbi="0" wins="1" losses="1" era="2.13"/>
		<player id="457477" first="Alejandro" last="De Aza" num="30" boxname="De Aza" rl="L" position="CF" current_position="CF" status="A" team_abbrev="CWS" team_id="145" parent_team_abbrev="CWS" parent_team_id="145" bat_order="1" game_position="CF" avg=".264" hr="16" rbi="60"/>
		<player id="457762" first="Bryan" last="Anderson" num="39" boxname="Anderson, B" rl="R" position="C" status="A" team_abbrev="CWS" team_id="145" parent_team_abbrev="CWS" parent_team_id="145" avg=".067" hr="0" rbi="2"/>
		<player id="458668" first="Jordan" last="Danks" num="20" boxname="Danks, Jd" rl="R" position="LF" status="A" team_abbrev="CWS" team_id="145" parent_team_abbrev="CWS" parent_team_id="145" avg=".234" hr="4" rbi="11"/>
		<player id="470462" first="Ramon" last="Troncoso" num="40" boxname="Troncoso" rl="R" position="P" status="A" team_abbrev="CWS" team_id="145" parent_team_abbrev="CWS" parent_team_id="145" avg=".000" hr="0" rbi="0" wins="1" losses="4" era="4.82"/>
		<player id="476134" first="Brian" last="Omogrosso" num="48" boxname="Omogrosso" rl="R" position="P" status="A" team_abbrev="CWS" team_id="145" parent_team_abbrev="CWS" parent_team_id="145" avg=".000" hr="0" rbi="0" wins="0" losses="2" era="9.37"/>
		<player id="489056" first="Charlie" last="Leesman" num="61" boxname="Leesman" rl="L" position="P" status="A" team_abbrev="CWS" team_id="145" parent_team_abbrev="CWS" parent_team_id="145" avg=".000" hr="0" rbi="0" wins="0" losses="0" era="7.43"/>
		<player id="493351" first="Alexei" last="Ramirez" num="10" boxname="Ramirez, Al" rl="R" position="SS" current_position="SS" status="A" team_abbrev="CWS" team_id="145" parent_team_abbrev="CWS" parent_team_id="145" bat_order="2" game_position="SS" avg=".282" hr="5" rbi="47"/>
		<player id="493364" first="Dayan" last="Viciedo" num="24" boxname="Viciedo" rl="R" position="LF" current_position="LF" status="A" team_abbrev="CWS" team_id="145" parent_team_abbrev="CWS" parent_team_id="145" bat_order="6" game_position="LF" avg=".263" hr="13" rbi="54"/>
		<player id="493596" first="Gordon" last="Beckham" num="15" boxname="Beckham, G" rl="R" position="2B" current_position="2B" status="A" team_abbrev="CWS" team_id="145" parent_team_abbrev="CWS" parent_team_id="145" bat_order="7" game_position="2B" avg=".269" hr="4" rbi="23"/>
		<player id="500779" first="Jose" last="Quintana" num="62" boxname="Quintana" rl="L" position="P" current_position="P" status="A" team_abbrev="CWS" team_id="145" parent_team_abbrev="CWS" parent_team_id="145" bat_order="0" game_position="P" avg=".000" hr="0" rbi="0" wins="8" losses="6" era="3.49"/>
		<player id="502327" first="Hector" last="Santiago" num="53" boxname="Santiago, H" rl="L" position="P" status="A" team_abbrev="CWS" team_id="145" parent_team_abbrev="CWS" parent_team_id="145" avg=".000" hr="0" rbi="0" wins="4" losses="9" era="3.53"/>
		<player id="502593" first="Jake" last="Petricka" num="68" boxname="Petricka" rl="R" position="P" status="A" team_abbrev="CWS" team_id="145" parent_team_abbrev="CWS" parent_team_id="145" avg=".000" hr="0" rbi="0" wins="1" losses="1" era="3.00"/>
		<player id="516589" first="Andre" last="Rienzo" num="64" boxname="Rienzo" rl="R" position="P" status="A" team_abbrev="CWS" team_id="145" parent_team_abbrev="CWS" parent_team_id="145" avg=".000" hr="0" rbi="0" wins="2" losses="2" era="5.04"/>
		<player id="518420" first="Dylan" last="Axelrod" num="33" boxname="Axelrod" rl="R" position="P" status="A" team_abbrev="CWS" team_id="145" parent_team_abbrev="CWS" parent_team_id="145" avg=".500" hr="0" rbi="0" wins="4" losses="10" era="5.72"/>
		<player id="518858" first="Nate" last="Jones" num="65" boxname="Jones, N" rl="R" position="P" current_position="P" status="A" team_abbrev="CWS" team_id="145" parent_team_abbrev="CWS" parent_team_id="145" avg=".000" hr="0" rbi="0" wins="4" losses="5" era="4.28"/>
		<player id="519242" first="Chris" last="Sale" num="49" boxname="Sale" rl="L" position="P" status="A" team_abbrev="CWS" team_id="145" parent_team_abbrev="CWS" parent_team_id="145" avg=".000" hr="0" rbi="0" wins="11" losses="13" era="2.97"/>
		<player id="541645" first="Avisail" last="Garcia" num="26" boxname="Garcia, A" rl="R" position="RF" current_position="RF" status="A" team_abbrev="CWS" team_id="145" parent_team_abbrev="CWS" parent_team_id="145" bat_order="5" game_position="RF" avg=".289" hr="5" rbi="28"/>
		<player id="543216" first="Conor" last="Gillaspie" num="12" boxname="Gillaspie" rl="R" position="3B" status="A" team_abbrev="CWS" team_id="145" parent_team_abbrev="CWS" parent_team_id="145" avg=".251" hr="12" rbi="38"/>
		<player id="543760" first="Marcus" last="Semien" num="5" boxname="Semien" rl="R" position="SS" current_position="3B" status="A" team_abbrev="CWS" team_id="145" parent_team_abbrev="CWS" parent_team_id="145" bat_order="8" game_position="3B" avg=".289" hr="0" rbi="4"/>
		<player id="543900" first="Daniel" last="Webb" num="60" boxname="Webb, D" rl="R" position="P" status="A" team_abbrev="CWS" team_id="145" parent_team_abbrev="CWS" parent_team_id="145" avg=".000" hr="0" rbi="0" wins="0" losses="0" era="4.15"/>
		<player id="544725" first="Leury" last="Garcia" num="28" boxname="Garcia, L" rl="R" position="SS" status="A" team_abbrev="CWS" team_id="145" parent_team_abbrev="CWS" parent_team_id="145" avg=".204" hr="0" rbi="2"/>
		<player id="544838" first="Miguel" last="Gonzalez" num="38" boxname="Gonzalez, M" rl="R" position="C" status="A" team_abbrev="CWS" team_id="145" parent_team_abbrev="CWS" parent_team_id="145" avg=".200" hr="0" rbi="0"/>
		<player id="572033" first="Josh" last="Phegley" num="36" boxname="Phegley" rl="R" position="C" current_position="C" status="A" team_abbrev="CWS" team_id="145" parent_team_abbrev="CWS" parent_team_id="145" bat_order="9" game_position="C" avg=".222" hr="4" rbi="22"/>
		<player id="592665" first="Addison" last="Reed" num="43" boxname="Reed, A" rl="R" position="P" current_position="P" status="A" team_abbrev="CWS" team_id="145" parent_team_abbrev="CWS" parent_team_id="145" avg=".000" hr="0" rbi="0" wins="5" losses="3" era="3.67"/>
		<player id="605304" first="Erik" last="Johnson" num="45" boxname="Johnson, E" rl="R" position="P" status="A" team_abbrev="CWS" team_id="145" parent_team_abbrev="CWS" parent_team_id="145" avg=".000" hr="0" rbi="0" wins="2" losses="2" era="2.82"/>
<coach position="manager" first="Robin" last="Ventura" id="123697" num="23"/><coach position="batting_coach" first="Jeff" last="Manto" id="118259" num="31"/><coach position="assistant_hitting_coach" first="Harold" last="Baines" id="110456" num="3"/><coach position="pitching_coach" first="Don" last="Cooper" id="112653" num="99"/><coach position="first_base_coach" first="Daryl" last="Boston" id="111257" num="17"/><coach position="third_base_coach" first="Joe" last="McEwing" id="136607" num="47"/><coach position="bench_coach" first="Mark" last="Parent" id="120218" num="8"/><coach position="bullpen_coach" first="Bobby" last="Thigpen" id="123230" num="58"/><coach position="bullpen_catcher" first="Mark" last="Salas" id="121628" num="59"/><coach position="special_assistant" first="Jim" last="Thome" id="123272" num=""/>	</team>
<umpires><umpire position="home" name="Mark Wegner" id="427533"/><umpire position="first" name="Tim Timmons" id="427509"/><umpire position="second" name="Mike Winters" id="427552"/><umpire position="third" name="Mike Muchlinski" id="483912"/></umpires></game>