<!--Copyright 2013 MLB Advanced Media, L.P.  Use of any content on this page acknowledges agreement to the terms posted here http://gdx.mlb.com/components/copyright.txt--><game venue="Chase Field" date="August 30, 2013">
	<team type="away" id="SF" name="San Francisco Giants">
		<player id="217096" first="Barry" last="Zito" num="75" boxname="Zito" rl="L" position="P" status="A" team_abbrev="SF" team_id="137" parent_team_abbrev="SF" parent_team_id="137" avg=".156" hr="0" rbi="2" wins="4" losses="10" era="5.81"/>
		<player id="285064" first="Ryan" last="Vogelsong" num="32" boxname="Vogelsong" rl="R" position="P" status="A" team_abbrev="SF" team_id="137" parent_team_abbrev="SF" parent_team_id="137" avg=".045" hr="0" rbi="2" wins="3" losses="4" era="5.58"/>
		<player id="340192" first="Marco" last="Scutaro" num="19" boxname="Scutaro" rl="R" position="2B" current_position="2B" status="A" team_abbrev="SF" team_id="137" parent_team_abbrev="SF" parent_team_id="137" bat_order="2" game_position="2B" avg=".299" hr="2" rbi="27"/>
		<player id="346793" first="Jeremy" last="Affeldt" num="41" boxname="Affeldt" rl="L" position="P" status="A" team_abbrev="SF" team_id="137" parent_team_abbrev="SF" parent_team_id="137" avg=".000" hr="0" rbi="0" wins="1" losses="4" era="3.51"/>
		<player id="400083" first="Andres" last="Torres" num="56" boxname="Torres, A" rl="R" position="LF" status="A" team_abbrev="SF" team_id="137" parent_team_abbrev="SF" parent_team_id="137" avg=".250" hr="2" rbi="21"/>
		<player id="425657" first="Javier" last="Lopez" num="49" boxname="Lopez, Ja" rl="L" position="P" current_position="P" status="A" team_abbrev="SF" team_id="137" parent_team_abbrev="SF" parent_team_id="137" avg=".000" hr="0" rbi="0" wins="2" losses="2" era="1.97"/>
		<player id="429985" first="Chad" last="Gaudin" num="57" boxname="Gaudin" rl="R" position="P" status="A" team_abbrev="SF" team_id="137" parent_team_abbrev="SF" parent_team_id="137" avg=".040" hr="0" rbi="1" wins="5" losses="2" era="3.06"/>
		<player id="430912" first="Matt" last="Cain" num="18" boxname="Cain, M" rl="R" position="P" status="A" team_abbrev="SF" team_id="137" parent_team_abbrev="SF" parent_team_id="137" avg=".068" hr="0" rbi="2" wins="8" losses="8" era="4.43"/>
		<player id="433586" first="Santiago" last="Casilla" num="46" boxname="Casilla, S" rl="R" position="P" current_position="P" status="A" team_abbrev="SF" team_id="137" parent_team_abbrev="SF" parent_team_id="137" avg=".000" hr="0" rbi="0" wins="5" losses="2" era="1.70"/>
		<player id="433589" first="Yusmeiro" last="Petit" num="52" boxname="Petit, Y" rl="R" position="P" status="A" team_abbrev="SF" team_id="137" parent_team_abbrev="SF" parent_team_id="137" avg=".000" hr="0" rbi="0" wins="1" losses="0" era="3.18"/>
		<player id="434636" first="Angel" last="Pagan" num="16" boxname="Pagan" rl="R" position="CF" current_position="CF" status="A" team_abbrev="SF" team_id="137" parent_team_abbrev="SF" parent_team_id="137" bat_order="1" game_position="CF" avg=".262" hr="3" rbi="24"/>
		<player id="435078" first="Joaquin" last="Arias" num="13" boxname="Arias" rl="R" position="3B" current_position="3B" status="A" team_abbrev="SF" team_id="137" parent_team_abbrev="SF" parent_team_id="137" avg=".275" hr="1" rbi="17"/>
		<player id="446861" first="Guillermo" last="Moscoso" num="34" boxname="Moscoso" rl="R" position="P" status="A" team_abbrev="SF" team_id="137" parent_team_abbrev="SF" parent_team_id="137" avg=".000" hr="0" rbi="0" wins="1" losses="2" era="4.87"/>
		<player id="452254" first="Hunter" last="Pence" num="8" boxname="Pence" rl="R" position="RF" current_position="RF" status="A" team_abbrev="SF" team_id="137" parent_team_abbrev="SF" parent_team_id="137" bat_order="5" game_position="RF" avg=".278" hr="16" rbi="67"/>
		<player id="453311" first="Tim" last="Lincecum" num="55" boxname="Lincecum" rl="R" position="P" current_position="P" status="A" team_abbrev="SF" team_id="137" parent_team_abbrev="SF" parent_team_id="137" bat_order="9" game_position="P" avg=".087" hr="0" rbi="1" wins="7" losses="13" era="4.55"/>
		<player id="453923" first="Gregor" last="Blanco" num="7" boxname="Blanco, G" rl="L" position="LF" current_position="LF" status="A" team_abbrev="SF" team_id="137" parent_team_abbrev="SF" parent_team_id="137" bat_order="8" game_position="LF" avg=".251" hr="1" rbi="33"/>
		<player id="457763" first="Buster" last="Posey" num="28" boxname="Posey" rl="R" position="C" current_position="C" status="A" team_abbrev="SF" team_id="137" parent_team_abbrev="SF" parent_team_id="137" bat_order="4" game_position="C" avg=".305" hr="14" rbi="66"/>
		<player id="466459" first="Sandy" last="Rosario" num="43" boxname="Rosario, S" rl="R" position="P" status="A" team_abbrev="SF" team_id="137" parent_team_abbrev="SF" parent_team_id="137" avg=".000" hr="0" rbi="0" wins="3" losses="1" era="2.77"/>
		<player id="466948" first="Jean" last="Machi" num="63" boxname="Machi" rl="R" position="P" status="A" team_abbrev="SF" team_id="137" parent_team_abbrev="SF" parent_team_id="137" avg=".000" hr="0" rbi="0" wins="2" losses="1" era="2.88"/>
		<player id="467055" first="Pablo" last="Sandoval" num="48" boxname="Sandoval" rl="R" position="3B" current_position="3B" status="A" team_abbrev="SF" team_id="137" parent_team_abbrev="SF" parent_team_id="137" bat_order="6" game_position="3B" avg=".269" hr="10" rbi="64"/>
		<player id="467726" first="Jose" last="Mijares" num="50" boxname="Mijares" rl="L" position="P" status="A" team_abbrev="SF" team_id="137" parent_team_abbrev="SF" parent_team_id="137" avg=".000" hr="0" rbi="0" wins="0" losses="3" era="4.24"/>
		<player id="473234" first="Tony" last="Abreu" num="10" boxname="Abreu" rl="R" position="2B" status="A" team_abbrev="SF" team_id="137" parent_team_abbrev="SF" parent_team_id="137" avg=".266" hr="1" rbi="7"/>
		<player id="474832" first="Brandon" last="Belt" num="9" boxname="Belt" rl="L" position="1B" current_position="1B" status="A" team_abbrev="SF" team_id="137" parent_team_abbrev="SF" parent_team_id="137" bat_order="3" game_position="1B" avg=".280" hr="15" rbi="51"/>
		<player id="489209" first="Brett" last="Pill" num="6" boxname="Pill" rl="R" position="1B" status="A" team_abbrev="SF" team_id="137" parent_team_abbrev="SF" parent_team_id="137" avg=".242" hr="2" rbi="8"/>
		<player id="489265" first="Sergio" last="Romo" num="54" boxname="Romo" rl="R" position="P" current_position="P" status="A" team_abbrev="SF" team_id="137" parent_team_abbrev="SF" parent_team_id="137" avg=".000" hr="0" rbi="0" wins="4" losses="6" era="2.61"/>
		<player id="516949" first="Hector" last="Sanchez" num="29" boxname="Sanchez, H" rl="R" position="C" status="A" team_abbrev="SF" team_id="137" parent_team_abbrev="SF" parent_team_id="137" avg=".243" hr="2" rbi="11"/>
		<player id="518516" first="Madison" last="Bumgarner" num="40" boxname="Bumgarner" rl="L" position="P" status="A" team_abbrev="SF" team_id="137" parent_team_abbrev="SF" parent_team_id="137" avg=".130" hr="0" rbi="4" wins="11" losses="9" era="2.91"/>
		<player id="523261" first="Roger" last="Kieschnick" num="22" boxname="Kieschnick" rl="R" position="RF" current_position="PH" status="A" team_abbrev="SF" team_id="137" parent_team_abbrev="SF" parent_team_id="137" avg=".225" hr="0" rbi="5"/>
		<player id="543063" first="Brandon" last="Crawford" num="35" boxname="Crawford, B" rl="R" position="SS" current_position="SS" status="A" team_abbrev="SF" team_id="137" parent_team_abbrev="SF" parent_team_id="137" bat_order="7" game_position="SS" avg=".267" hr="8" rbi="40"/>
		<player id="592464" first="Mike" last="Kickham" num="59" boxname="Kickham" rl="L" position="P" status="A" team_abbrev="SF" team_id="137" parent_team_abbrev="SF" parent_team_id="137" avg=".167" hr="0" rbi="0" wins="0" losses="3" era="10.72"/>
<coach position="manager" first="Bruce" last="Bochy" id="111136" num="15"/><coach position="batting_coach" first="Hensley" last="Meulens" id="119004" num="31"/><coach position="assistant_hitting_coach" first="Joe" last="Lefebvre" id="117625" num="5"/><coach position="pitching_coach" first="Dave" last="Righetti" id="121201" num="33"/><coach position="first_base_coach" first="Roberto" last="Kelly" id="116959" num="39"/><coach position="third_base_coach" first="Tim" last="Flannery" id="114220" num="1"/><coach position="bench_coach" first="Ron" last="Wotus" id="124588" num="17"/><coach position="bullpen_coach" first="Mark" last="Gardner" id="114610" num="26"/><coach position="bullpen_catcher" first="Bill" last="Hayes" id="115647" num="58"/><coach position="special_assistant" first="Joey" last="Amalfitano" id="110213" num=""/><coach position="special_assistant" first="Jim" last="Davenport" id="113081" num=""/><coach position="special_assistant" first="J.T." last="Snow" id="122497" num=""/>	</team>
	<team type="home" id="ARI" name="Arizona Diamondbacks">
		<player id="136767" first="Eric" last="Chavez" num="12" boxname="Chavez, Er" rl="R" position="3B" current_position="PH" status="A" team_abbrev="ARI" team_id="109" parent_team_abbrev="ARI" parent_team_id="109" avg=".290" hr="9" rbi="40"/>
		<player id="217100" first="Willie" last="Bloomquist" num="18" boxname="Bloomquist" rl="R" position="2B" current_position="PH" status="A" team_abbrev="ARI" team_id="109" parent_team_abbrev="ARI" parent_team_id="109" avg=".316" hr="0" rbi="9"/>
		<player id="407816" first="J.J." last="Putz" num="40" boxname="Putz" rl="R" position="P" status="A" team_abbrev="ARI" team_id="109" parent_team_abbrev="ARI" parent_team_id="109" avg=".000" hr="0" rbi="0" wins="3" losses="1" era="2.43"/>
		<player id="408242" first="Wil" last="Nieves" num="27" boxname="Nieves" rl="R" position="C" status="A" team_abbrev="ARI" team_id="109" parent_team_abbrev="ARI" parent_team_id="109" avg=".322" hr="1" rbi="22"/>
		<player id="425496" first="Cody" last="Ross" num="7" boxname="Ross, C" rl="L" position="RF" status="A" team_abbrev="ARI" team_id="109" parent_team_abbrev="ARI" parent_team_id="109" avg=".278" hr="8" rbi="38"/>
		<player id="425514" first="Heath" last="Bell" num="21" boxname="Bell" rl="R" position="P" status="A" team_abbrev="ARI" team_id="109" parent_team_abbrev="ARI" parent_team_id="109" avg=".000" hr="0" rbi="0" wins="5" losses="2" era="4.21"/>
		<player id="431094" first="Aaron" last="Hill" num="2" boxname="Hill, A" rl="R" position="2B" current_position="2B" status="A" team_abbrev="ARI" team_id="109" parent_team_abbrev="ARI" parent_team_id="109" bat_order="5" game_position="2B" avg=".316" hr="9" rbi="35"/>
		<player id="435221" first="Brandon" last="McCarthy" num="32" boxname="McCarthy" rl="R" position="P" status="A" team_abbrev="ARI" team_id="109" parent_team_abbrev="ARI" parent_team_id="109" avg=".000" hr="0" rbi="0" wins="3" losses="8" era="5.03"/>
		<player id="445988" first="Martin" last="Prado" num="14" boxname="Prado" rl="R" position="3B" current_position="3B" status="A" team_abbrev="ARI" team_id="109" parent_team_abbrev="ARI" parent_team_id="109" bat_order="4" game_position="3B" avg=".284" hr="13" rbi="71"/>
		<player id="446899" first="Brad" last="Ziegler" num="29" boxname="Ziegler" rl="R" position="P" current_position="P" status="A" team_abbrev="ARI" team_id="109" parent_team_abbrev="ARI" parent_team_id="109" avg=".000" hr="0" rbi="0" wins="7" losses="1" era="2.52"/>
		<player id="460060" first="Cliff" last="Pennington" num="4" boxname="Pennington" rl="R" position="SS" status="A" team_abbrev="ARI" team_id="109" parent_team_abbrev="ARI" parent_team_id="109" avg=".230" hr="1" rbi="18"/>
		<player id="467827" first="Gerardo" last="Parra" num="8" boxname="Parra, G" rl="L" position="CF" current_position="RF" status="A" team_abbrev="ARI" team_id="109" parent_team_abbrev="ARI" parent_team_id="109" bat_order="1" game_position="RF" avg=".272" hr="10" rbi="39"/>
		<player id="471083" first="Miguel" last="Montero" num="26" boxname="Montero, M" rl="R" position="C" current_position="C" status="A" team_abbrev="ARI" team_id="109" parent_team_abbrev="ARI" parent_team_id="109" bat_order="6" game_position="C" avg=".228" hr="9" rbi="34"/>
		<player id="475054" first="Chaz" last="Roe" num="34" boxname="Roe" rl="R" position="P" status="A" team_abbrev="ARI" team_id="109" parent_team_abbrev="ARI" parent_team_id="109" avg=".000" hr="0" rbi="0" wins="1" losses="0" era="6.23"/>
		<player id="489119" first="Wade" last="Miley" num="36" boxname="Miley" rl="L" position="P" status="A" team_abbrev="ARI" team_id="109" parent_team_abbrev="ARI" parent_team_id="109" avg=".102" hr="1" rbi="5" wins="9" losses="9" era="3.55"/>
		<player id="491159" first="Joe" last="Thatcher" num="57" boxname="Thatcher" rl="L" position="P" status="A" team_abbrev="ARI" team_id="109" parent_team_abbrev="ARI" parent_team_id="109" avg=".000" hr="0" rbi="0" wins="3" losses="1" era="3.28"/>
		<player id="501789" first="Will" last="Harris" num="38" boxname="Harris" rl="R" position="P" current_position="P" status="A" team_abbrev="ARI" team_id="109" parent_team_abbrev="ARI" parent_team_id="109" avg=".000" hr="0" rbi="0" wins="2" losses="0" era="2.25"/>
		<player id="502239" first="Trevor" last="Cahill" num="35" boxname="Cahill" rl="R" position="P" status="A" team_abbrev="ARI" team_id="109" parent_team_abbrev="ARI" parent_team_id="109" avg=".105" hr="0" rbi="5" wins="5" losses="10" era="4.39"/>
		<player id="502671" first="Paul" last="Goldschmidt" num="44" boxname="Goldschmidt" rl="R" position="1B" current_position="1B" status="A" team_abbrev="ARI" team_id="109" parent_team_abbrev="ARI" parent_team_id="109" bat_order="3" game_position="1B" avg=".300" hr="31" rbi="104"/>
		<player id="517414" first="Randall" last="Delgado" num="48" boxname="Delgado, R" rl="R" position="P" current_position="P" status="A" team_abbrev="ARI" team_id="109" parent_team_abbrev="ARI" parent_team_id="109" bat_order="9" game_position="P" avg=".238" hr="0" rbi="0" wins="4" losses="4" era="3.87"/>
		<player id="518567" first="Josh" last="Collmenter" num="55" boxname="Collmenter" rl="R" position="P" status="A" team_abbrev="ARI" team_id="109" parent_team_abbrev="ARI" parent_team_id="109" avg=".100" hr="0" rbi="0" wins="4" losses="2" era="2.75"/>
		<player id="519186" first="Matt" last="Reynolds" num="45" boxname="Reynolds, M" rl="L" position="P" status="A" team_abbrev="ARI" team_id="109" parent_team_abbrev="ARI" parent_team_id="109" avg=".000" hr="0" rbi="0" wins="0" losses="2" era="1.98"/>
		<player id="542999" first="Tony" last="Campana" num="19" boxname="Campana" rl="L" position="CF" current_position="PR" status="A" team_abbrev="ARI" team_id="109" parent_team_abbrev="ARI" parent_team_id="109" avg=".314" hr="0" rbi="0"/>
		<player id="543339" first="Daniel" last="Hudson" num="41" boxname="Hudson, D" rl="R" position="P" status="A" team_abbrev="ARI" team_id="109" parent_team_abbrev="ARI" parent_team_id="109" avg=".000" hr="0" rbi="0" wins="0" losses="0" era="-"/>
		<player id="544369" first="Didi" last="Gregorius" num="1" boxname="Gregorius" rl="R" position="SS" current_position="SS" status="A" team_abbrev="ARI" team_id="109" parent_team_abbrev="ARI" parent_team_id="109" bat_order="8" game_position="SS" avg=".263" hr="5" rbi="21"/>
		<player id="545001" first="Eury" last="De La Rosa" num="56" boxname="De La Rosa, E" rl="L" position="P" status="A" team_abbrev="ARI" team_id="109" parent_team_abbrev="ARI" parent_team_id="109" avg=".000" hr="0" rbi="0" wins="0" losses="1" era="0.84"/>
		<player id="571578" first="Patrick" last="Corbin" num="46" boxname="Corbin" rl="L" position="P" status="A" team_abbrev="ARI" team_id="109" parent_team_abbrev="ARI" parent_team_id="109" avg=".140" hr="0" rbi="3" wins="13" losses="4" era="2.79"/>
		<player id="572041" first="A.J." last="Pollock" num="11" boxname="Pollock" rl="R" position="CF" current_position="CF" status="A" team_abbrev="ARI" team_id="109" parent_team_abbrev="ARI" parent_team_id="109" bat_order="7" game_position="CF" avg=".253" hr="7" rbi="33"/>
		<player id="594809" first="Adam" last="Eaton" num="6" boxname="Eaton" rl="L" position="CF" current_position="LF" status="A" team_abbrev="ARI" team_id="109" parent_team_abbrev="ARI" parent_team_id="109" bat_order="2" game_position="LF" avg=".263" hr="2" rbi="12"/>
<coach position="manager" first="Kirk" last="Gibson" id="114752" num="23"/><coach position="batting_coach" first="Don" last="Baylor" id="110719" num="25"/><coach position="assistant_hitting_coach" first="Turner" last="Ward" id="123930" num="15"/><coach position="pitching_coach" first="Charles" last="Nagy" id="119640" num="50"/><coach position="first_base_coach" first="Steve" last="Sax" id="121732" num="5"/><coach position="third_base_coach" first="Matt" last="Williams" id="124326" num="9"/><coach position="bench_coach" first="Alan" last="Trammell" id="123437" num="3"/><coach position="bullpen_coach" first="Glenn" last="Sherlock" id="427468" num="53"/><coach position="bullpen_catcher" first="Jeff" last="Motuzas" id="432795" num="82"/>	</team>
<umpires><umpire position="home" name="Bill Miller" id="427344"/><umpire position="first" name="Todd Tichenor" id="429805"/><umpire position="second" name="CB Bucknor" id="427044"/><umpire position="third" name="Dale Scott" id="427457"/></umpires></game>