<!--Copyright 2013 MLB Advanced Media, L.P.  Use of any content on this page acknowledges agreement to the terms posted here http://gdx.mlb.com/components/copyright.txt--><game venue="Yankee Stadium" date="April 12, 2013">
	<team type="away" id="BAL" name="Baltimore Orioles">
		<player id="400140" first="Wilson" last="Betemit" num="24" boxname="Betemit" rl="R" position="3B" status="A" team_abbrev="BAL" team_id="110" parent_team_abbrev="BAL" parent_team_id="110" avg=".000" hr="0" rbi="0"/>
		<player id="406878" first="Brian" last="Roberts" num="1" boxname="Roberts, B" rl="R" position="2B" status="A" team_abbrev="BAL" team_id="110" parent_team_abbrev="BAL" parent_team_id="110" avg=".417" hr="0" rbi="1"/>
		<player id="429666" first="J.J." last="Hardy" num="2" boxname="Hardy" rl="R" position="SS" current_position="SS" status="A" team_abbrev="BAL" team_id="110" parent_team_abbrev="BAL" parent_team_id="110" bat_order="6" game_position="SS" avg=".200" hr="2" rbi="5"/>
		<player id="430945" first="Adam" last="Jones" num="10" boxname="Jones, Ad" rl="R" position="CF" current_position="CF" status="A" team_abbrev="BAL" team_id="110" parent_team_abbrev="BAL" parent_team_id="110" bat_order="3" game_position="CF" avg=".462" hr="1" rbi="10"/>
		<player id="434628" first="Jason" last="Hammel" num="39" boxname="Hammel" rl="R" position="P" status="A" team_abbrev="BAL" team_id="110" parent_team_abbrev="BAL" parent_team_id="110" avg=".000" hr="0" rbi="0" wins="1" losses="1" era="4.97"/>
		<player id="434661" first="Nate" last="McLouth" num="9" boxname="McLouth" rl="R" position="LF" status="A" team_abbrev="BAL" team_id="110" parent_team_abbrev="BAL" parent_team_id="110" avg=".241" hr="0" rbi="1"/>
		<player id="446308" first="Matt" last="Wieters" num="32" boxname="Wieters" rl="R" position="C" current_position="C" status="A" team_abbrev="BAL" team_id="110" parent_team_abbrev="BAL" parent_team_id="110" bat_order="4" game_position="C" avg=".241" hr="1" rbi="3"/>
		<player id="447736" first="Chris" last="Dickerson" num="60" boxname="Dickerson" rl="L" position="LF" status="A" team_abbrev="BAL" team_id="110" parent_team_abbrev="BAL" parent_team_id="110" avg=".333" hr="0" rbi="0"/>
		<player id="448801" first="Chris" last="Davis" num="19" boxname="Davis, C" rl="R" position="1B" current_position="1B" status="A" team_abbrev="BAL" team_id="110" parent_team_abbrev="BAL" parent_team_id="110" bat_order="5" game_position="1B" avg=".400" hr="6" rbi="19"/>
		<player id="451085" first="Brian" last="Matusz" num="17" boxname="Matusz" rl="L" position="P" status="A" team_abbrev="BAL" team_id="110" parent_team_abbrev="BAL" parent_team_id="110" avg=".000" hr="0" rbi="0" wins="1" losses="0" era="3.00"/>
		<player id="453562" first="Jake" last="Arrieta" num="34" boxname="Arrieta" rl="R" position="P" status="A" team_abbrev="BAL" team_id="110" parent_team_abbrev="BAL" parent_team_id="110" avg=".000" hr="0" rbi="0" wins="0" losses="0" era="7.20"/>
		<player id="455976" first="Nick" last="Markakis" num="21" boxname="Markakis" rl="L" position="RF" current_position="RF" status="A" team_abbrev="BAL" team_id="110" parent_team_abbrev="BAL" parent_team_id="110" bat_order="1" game_position="RF" avg=".300" hr="1" rbi="3"/>
		<player id="456068" first="Miguel" last="Gonzalez" num="50" boxname="Gonzalez, M" rl="R" position="P" current_position="P" status="A" team_abbrev="BAL" team_id="110" parent_team_abbrev="BAL" parent_team_id="110" bat_order="0" game_position="P" avg=".000" hr="0" rbi="0" wins="1" losses="0" era="2.84"/>
		<player id="456665" first="Steve" last="Pearce" num="28" boxname="Pearce" rl="R" position="1B" current_position="DH" status="A" team_abbrev="BAL" team_id="110" parent_team_abbrev="BAL" parent_team_id="110" bat_order="8" game_position="DH" avg=".000" hr="0" rbi="0"/>
		<player id="458210" first="Alexi" last="Casilla" num="12" boxname="Casilla, A" rl="R" position="2B" current_position="2B" status="A" team_abbrev="BAL" team_id="110" parent_team_abbrev="BAL" parent_team_id="110" bat_order="9" game_position="2B" avg=".125" hr="0" rbi="0"/>
		<player id="460003" first="Taylor" last="Teagarden" num="31" boxname="Teagarden" rl="R" position="C" status="A" team_abbrev="BAL" team_id="110" parent_team_abbrev="BAL" parent_team_id="110" avg=".000" hr="0" rbi="0"/>
		<player id="460099" first="Nolan" last="Reimold" num="14" boxname="Reimold" rl="R" position="LF" current_position="LF" status="A" team_abbrev="BAL" team_id="110" parent_team_abbrev="BAL" parent_team_id="110" bat_order="7" game_position="LF" avg=".200" hr="0" rbi="0"/>
		<player id="461856" first="Troy" last="Patton" num="40" boxname="Patton" rl="L" position="P" current_position="P" status="A" team_abbrev="BAL" team_id="110" parent_team_abbrev="BAL" parent_team_id="110" avg=".000" hr="0" rbi="0" wins="0" losses="0" era="0.00"/>
		<player id="462382" first="Jim" last="Johnson" num="43" boxname="Johnson, J" rl="R" position="P" status="A" team_abbrev="BAL" team_id="110" parent_team_abbrev="BAL" parent_team_id="110" avg=".000" hr="0" rbi="0" wins="0" losses="1" era="0.00"/>
		<player id="467008" first="Pedro" last="Strop" num="47" boxname="Strop" rl="R" position="P" current_position="P" status="A" team_abbrev="BAL" team_id="110" parent_team_abbrev="BAL" parent_team_id="110" avg=".000" hr="0" rbi="0" wins="0" losses="0" era="6.75"/>
		<player id="475247" first="Ryan" last="Flaherty" num="3" boxname="Flaherty" rl="R" position="2B" status="A" team_abbrev="BAL" team_id="110" parent_team_abbrev="BAL" parent_team_id="110" avg=".056" hr="0" rbi="0"/>
		<player id="488984" first="Tommy" last="Hunter" num="29" boxname="Hunter, T" rl="R" position="P" current_position="P" status="A" team_abbrev="BAL" team_id="110" parent_team_abbrev="BAL" parent_team_id="110" avg=".000" hr="0" rbi="0" wins="0" losses="1" era="7.36"/>
		<player id="489002" first="Steve" last="Johnson" num="52" boxname="Johnson, S" rl="R" position="P" status="A" team_abbrev="BAL" team_id="110" parent_team_abbrev="BAL" parent_team_id="110" avg=".000" hr="0" rbi="0" wins="0" losses="0" era="-"/>
		<player id="493159" first="Tsuyoshi" last="Wada" num="18" boxname="Wada" rl="L" position="P" status="A" team_abbrev="BAL" team_id="110" parent_team_abbrev="BAL" parent_team_id="110" avg=".000" hr="0" rbi="0" wins="0" losses="0" era="-"/>
		<player id="501957" first="Chris" last="Tillman" num="30" boxname="Tillman" rl="R" position="P" status="A" team_abbrev="BAL" team_id="110" parent_team_abbrev="BAL" parent_team_id="110" avg=".000" hr="0" rbi="0" wins="0" losses="0" era="7.00"/>
		<player id="503285" first="Darren" last="O'Day" num="56" boxname="O'Day" rl="R" position="P" status="A" team_abbrev="BAL" team_id="110" parent_team_abbrev="BAL" parent_team_id="110" avg=".000" hr="0" rbi="0" wins="1" losses="0" era="0.00"/>
		<player id="519008" first="T.J." last="McFarland" num="66" boxname="McFarland" rl="L" position="P" status="A" team_abbrev="BAL" team_id="110" parent_team_abbrev="BAL" parent_team_id="110" avg=".000" hr="0" rbi="0" wins="0" losses="0" era="0.00"/>
		<player id="592518" first="Manny" last="Machado" num="13" boxname="Machado" rl="R" position="3B" current_position="3B" status="A" team_abbrev="BAL" team_id="110" parent_team_abbrev="BAL" parent_team_id="110" bat_order="2" game_position="3B" avg=".256" hr="1" rbi="4"/>
		<player id="612672" first="Wei-Yin" last="Chen" num="16" boxname="Chen" rl="L" position="P" status="A" team_abbrev="BAL" team_id="110" parent_team_abbrev="BAL" parent_team_id="110" avg=".000" hr="0" rbi="0" wins="0" losses="1" era="3.75"/>
<coach position="manager" first="Buck" last="Showalter" id="427469" num="26"/><coach position="batting_coach" first="Jim" last="Presley" id="120755" num="15"/><coach position="assistant_hitting_coach" first="Einar" last="Diaz" id="113330" num=""/><coach position="pitching_coach" first="Rick" last="Adair" id="547748" num="41"/><coach position="first_base_coach" first="Wayne" last="Kirby" id="117114" num="23"/><coach position="third_base_coach" first="Bobby" last="Dickerson" id="433638" num="11"/><coach position="bench_coach" first="John" last="Russell" id="121571" num="77"/><coach position="bullpen_coach" first="Bill" last="Castro" id="112130" num="39"/><coach position="bullpen_catcher" first="Rudy" last="Arias" id="608791" num="62"/>	</team>
	<team type="home" id="NYY" name="New York Yankees">
		<player id="116539" first="Derek" last="Jeter" num="2" boxname="Jeter" rl="R" position="SS" status="A" team_abbrev="NYY" team_id="147" parent_team_abbrev="NYY" parent_team_id="147" avg=".000" hr="0" rbi="0"/>
		<player id="120485" first="Andy" last="Pettitte" num="46" boxname="Pettitte" rl="L" position="P" status="A" team_abbrev="NYY" team_id="147" parent_team_abbrev="NYY" parent_team_id="147" avg=".000" hr="0" rbi="0" wins="2" losses="0" era="1.20"/>
		<player id="121250" first="Mariano" last="Rivera" num="42" boxname="Rivera, Ma" rl="R" position="P" current_position="P" status="A" team_abbrev="NYY" team_id="147" parent_team_abbrev="NYY" parent_team_id="147" avg=".000" hr="0" rbi="0" wins="0" losses="0" era="4.50"/>
		<player id="121347" first="Alex" last="Rodriguez" num="13" boxname="Rodriguez, Al" rl="R" position="3B" status="A" team_abbrev="NYY" team_id="147" parent_team_abbrev="NYY" parent_team_id="147" avg=".000" hr="0" rbi="0"/>
		<player id="150484" first="Vernon" last="Wells" num="12" boxname="Wells, V" rl="R" position="LF" current_position="LF" status="A" team_abbrev="NYY" team_id="147" parent_team_abbrev="NYY" parent_team_id="147" bat_order="5" game_position="LF" avg=".360" hr="2" rbi="4"/>
		<player id="282332" first="CC" last="Sabathia" num="52" boxname="Sabathia" rl="L" position="P" current_position="P" status="A" team_abbrev="NYY" team_id="147" parent_team_abbrev="NYY" parent_team_id="147" bat_order="0" game_position="P" avg=".000" hr="0" rbi="0" wins="1" losses="1" era="3.00"/>
		<player id="400085" first="Ichiro" last="Suzuki" num="31" boxname="Suzuki, I" rl="R" position="RF" current_position="RF" status="A" team_abbrev="NYY" team_id="147" parent_team_abbrev="NYY" parent_team_id="147" bat_order="6" game_position="RF" avg=".185" hr="1" rbi="3"/>
		<player id="400098" first="Travis" last="Hafner" num="33" boxname="Hafner" rl="R" position="D" current_position="DH" status="A" team_abbrev="NYY" team_id="147" parent_team_abbrev="NYY" parent_team_id="147" bat_order="4" game_position="DH" avg=".333" hr="2" rbi="6"/>
		<player id="407489" first="Lyle" last="Overbay" num="55" boxname="Overbay" rl="L" position="1B" current_position="1B" status="A" team_abbrev="NYY" team_id="147" parent_team_abbrev="NYY" parent_team_id="147" bat_order="8" game_position="1B" avg=".250" hr="1" rbi="5"/>
		<player id="407893" first="Mark" last="Teixeira" num="25" boxname="Teixeira" rl="R" position="1B" status="A" team_abbrev="NYY" team_id="147" parent_team_abbrev="NYY" parent_team_id="147" avg=".000" hr="0" rbi="0"/>
		<player id="425903" first="Kevin" last="Youkilis" num="36" boxname="Youkilis" rl="R" position="3B" current_position="3B" status="A" team_abbrev="NYY" team_id="147" parent_team_abbrev="NYY" parent_team_id="147" bat_order="3" game_position="3B" avg=".367" hr="2" rbi="6"/>
		<player id="429664" first="Robinson" last="Cano" num="24" boxname="Cano" rl="R" position="2B" current_position="2B" status="A" team_abbrev="NYY" team_id="147" parent_team_abbrev="NYY" parent_team_id="147" bat_order="2" game_position="2B" avg=".303" hr="3" rbi="7"/>
		<player id="434158" first="Curtis" last="Granderson" num="14" boxname="Granderson" rl="R" position="CF" status="A" team_abbrev="NYY" team_id="147" parent_team_abbrev="NYY" parent_team_id="147" avg=".000" hr="0" rbi="0"/>
		<player id="434624" first="Jayson" last="Nix" num="17" boxname="Nix, J" rl="R" position="2B" current_position="SS" status="A" team_abbrev="NYY" team_id="147" parent_team_abbrev="NYY" parent_team_id="147" avg=".231" hr="1" rbi="2"/>
		<player id="450204" first="Ben" last="Francisco" num="45" boxname="Francisco, B" rl="R" position="LF" status="A" team_abbrev="NYY" team_id="147" parent_team_abbrev="NYY" parent_team_id="147" avg=".000" hr="0" rbi="0"/>
		<player id="453269" first="Brennan" last="Boesch" num="22" boxname="Boesch" rl="L" position="LF" status="A" team_abbrev="NYY" team_id="147" parent_team_abbrev="NYY" parent_team_id="147" avg=".250" hr="1" rbi="2"/>
		<player id="455755" first="Chris" last="Stewart" num="19" boxname="Stewart, C" rl="R" position="C" status="A" team_abbrev="NYY" team_id="147" parent_team_abbrev="NYY" parent_team_id="147" avg=".200" hr="0" rbi="0"/>
		<player id="456488" first="Eduardo" last="Nunez" num="26" boxname="Nunez, E" rl="R" position="SS" current_position="SS" status="A" team_abbrev="NYY" team_id="147" parent_team_abbrev="NYY" parent_team_id="147" bat_order="7" game_position="SS" avg=".250" hr="0" rbi="1"/>
		<player id="457429" first="Boone" last="Logan" num="48" boxname="Logan" rl="L" position="P" status="A" team_abbrev="NYY" team_id="147" parent_team_abbrev="NYY" parent_team_id="147" avg=".000" hr="0" rbi="0" wins="0" losses="0" era="3.38"/>
		<player id="458731" first="Brett" last="Gardner" num="11" boxname="Gardner" rl="L" position="LF" current_position="CF" status="A" team_abbrev="NYY" team_id="147" parent_team_abbrev="NYY" parent_team_id="147" bat_order="1" game_position="CF" avg=".257" hr="1" rbi="4"/>
		<player id="461833" first="Phil" last="Hughes" num="65" boxname="Hughes, P" rl="R" position="P" status="A" team_abbrev="NYY" team_id="147" parent_team_abbrev="NYY" parent_team_id="147" avg=".000" hr="0" rbi="0" wins="0" losses="1" era="6.75"/>
		<player id="465041" first="Francisco" last="Cervelli" num="29" boxname="Cervelli" rl="R" position="C" current_position="C" status="A" team_abbrev="NYY" team_id="147" parent_team_abbrev="NYY" parent_team_id="147" bat_order="9" game_position="C" avg=".353" hr="1" rbi="6"/>
		<player id="467100" first="Ivan" last="Nova" num="47" boxname="Nova" rl="R" position="P" status="A" team_abbrev="NYY" team_id="147" parent_team_abbrev="NYY" parent_team_id="147" avg=".000" hr="0" rbi="0" wins="0" losses="1" era="7.71"/>
		<player id="475479" first="David" last="Phelps" num="41" boxname="Phelps, D" rl="R" position="P" status="A" team_abbrev="NYY" team_id="147" parent_team_abbrev="NYY" parent_team_id="147" avg=".000" hr="0" rbi="0" wins="0" losses="0" era="6.75"/>
		<player id="476589" first="Adam" last="Warren" num="43" boxname="Warren" rl="R" position="P" status="A" team_abbrev="NYY" team_id="147" parent_team_abbrev="NYY" parent_team_id="147" avg=".000" hr="0" rbi="0" wins="0" losses="0" era="1.23"/>
		<player id="493133" first="Hiroki" last="Kuroda" num="18" boxname="Kuroda" rl="R" position="P" status="A" team_abbrev="NYY" team_id="147" parent_team_abbrev="NYY" parent_team_id="147" avg=".000" hr="0" rbi="0" wins="1" losses="1" era="6.75"/>
		<player id="501381" first="Michael" last="Pineda" num="35" boxname="Pineda" rl="R" position="P" status="A" team_abbrev="NYY" team_id="147" parent_team_abbrev="NYY" parent_team_id="147" avg=".000" hr="0" rbi="0" wins="0" losses="0" era="-"/>
		<player id="501627" first="Cesar" last="Cabral" num="71" boxname="Cabral" rl="L" position="P" status="A" team_abbrev="NYY" team_id="147" parent_team_abbrev="NYY" parent_team_id="147" avg=".000" hr="0" rbi="0" wins="0" losses="0" era="-"/>
		<player id="501955" first="Joba" last="Chamberlain" num="62" boxname="Chamberlain" rl="R" position="P" status="A" team_abbrev="NYY" team_id="147" parent_team_abbrev="NYY" parent_team_id="147" avg=".000" hr="0" rbi="0" wins="0" losses="0" era="13.50"/>
		<player id="502085" first="David" last="Robertson" num="30" boxname="Robertson" rl="R" position="P" status="A" team_abbrev="NYY" team_id="147" parent_team_abbrev="NYY" parent_team_id="147" avg=".000" hr="0" rbi="0" wins="0" losses="0" era="0.00"/>
		<player id="518875" first="Shawn" last="Kelley" num="27" boxname="Kelley" rl="R" position="P" status="A" team_abbrev="NYY" team_id="147" parent_team_abbrev="NYY" parent_team_id="147" avg=".000" hr="0" rbi="0" wins="0" losses="0" era="10.13"/>
<coach position="manager" first="Joe" last="Girardi" id="114833" num="28"/><coach position="batting_coach" first="Kevin" last="Long" id="438989" num="54"/><coach position="pitching_coach" first="Larry" last="Rothschild" id="121495" num="58"/><coach position="first_base_coach" first="Mick" last="Kelleher" id="116918" num="50"/><coach position="third_base_coach" first="Rob" last="Thomson" id="479080" num="59"/><coach position="bench_coach" first="Tony" last="Pena" id="120370" num="56"/><coach position="bullpen_coach" first="Mike" last="Harkey" id="115476" num="57"/><coach position="bullpen_catcher" first="Roman" last="Rodriguez" id="459550" num="88"/>	</team>
<umpires><umpire position="home" name="Dan Bellino" id="483564"/><umpire position="first" name="Larry Vanover" id="427520"/><umpire position="second" name="Manny Gonzalez" id="484499"/><umpire position="third" name="Wally Bell" id="427026"/></umpires></game>