<!--Copyright 2013 MLB Advanced Media, L.P.  Use of any content on this page acknowledges agreement to the terms posted here http://gdx.mlb.com/components/copyright.txt--><game venue="AT&amp;T Park" date="August 7, 2013">
	<team type="away" id="MIL" name="Milwaukee Brewers">
		<player id="133380" first="Aramis" last="Ramirez" num="16" boxname="Ramirez, Ar" rl="R" position="3B" status="A" team_abbrev="MIL" team_id="158" parent_team_abbrev="MIL" parent_team_id="158" avg=".271" hr="5" rbi="26"/>
		<player id="283166" first="Michael" last="Gonzalez" num="51" boxname="Gonzalez, M" rl="L" position="P" current_position="P" status="A" team_abbrev="MIL" team_id="158" parent_team_abbrev="MIL" parent_team_id="158" avg=".000" hr="0" rbi="0" wins="0" losses="3" era="4.05"/>
		<player id="346798" first="Kyle" last="Lohse" num="26" boxname="Lohse" rl="R" position="P" status="A" team_abbrev="MIL" team_id="158" parent_team_abbrev="MIL" parent_team_id="158" avg=".167" hr="0" rbi="2" wins="7" losses="7" era="3.23"/>
		<player id="430001" first="Rickie" last="Weeks" num="23" boxname="Weeks, R" rl="R" position="2B" current_position="2B" status="A" team_abbrev="MIL" team_id="158" parent_team_abbrev="MIL" parent_team_id="158" bat_order="1" game_position="2B" avg=".211" hr="10" rbi="24"/>
		<player id="430611" first="Corey" last="Hart" num="1" boxname="Hart" rl="R" position="1B" status="A" team_abbrev="MIL" team_id="158" parent_team_abbrev="MIL" parent_team_id="158" avg=".000" hr="0" rbi="0"/>
		<player id="435358" first="Yuniesky" last="Betancourt" num="3" boxname="Betancourt, Y" rl="R" position="1B" current_position="3B" status="A" team_abbrev="MIL" team_id="158" parent_team_abbrev="MIL" parent_team_id="158" bat_order="7" game_position="1B" avg=".210" hr="12" rbi="38"/>
		<player id="445213" first="Brandon" last="Kintzler" num="53" boxname="Kintzler" rl="R" position="P" status="A" team_abbrev="MIL" team_id="158" parent_team_abbrev="MIL" parent_team_id="158" avg=".000" hr="0" rbi="0" wins="3" losses="0" era="2.60"/>
		<player id="446099" first="John" last="Axford" num="59" boxname="Axford" rl="R" position="P" status="A" team_abbrev="MIL" team_id="158" parent_team_abbrev="MIL" parent_team_id="158" avg=".000" hr="0" rbi="0" wins="5" losses="5" era="4.47"/>
		<player id="449104" first="Jim" last="Henderson" num="29" boxname="Henderson" rl="R" position="P" status="A" team_abbrev="MIL" team_id="158" parent_team_abbrev="MIL" parent_team_id="158" avg=".000" hr="0" rbi="0" wins="3" losses="3" era="1.88"/>
		<player id="449161" first="Mark" last="Rogers" num="37" boxname="Rogers, M" rl="R" position="P" status="A" team_abbrev="MIL" team_id="158" parent_team_abbrev="MIL" parent_team_id="158" avg=".000" hr="0" rbi="0" wins="0" losses="0" era="-"/>
		<player id="451143" first="Mat" last="Gamel" num="24" boxname="Gamel" rl="R" position="1B" status="A" team_abbrev="MIL" team_id="158" parent_team_abbrev="MIL" parent_team_id="158" avg=".000" hr="0" rbi="0"/>
		<player id="451596" first="Yovani" last="Gallardo" num="49" boxname="Gallardo" rl="R" position="P" status="A" team_abbrev="MIL" team_id="158" parent_team_abbrev="MIL" parent_team_id="158" avg=".238" hr="2" rbi="3" wins="8" losses="9" era="4.91"/>
		<player id="451628" first="Alfredo" last="Figaro" num="45" boxname="Figaro" rl="R" position="P" current_position="P" status="A" team_abbrev="MIL" team_id="158" parent_team_abbrev="MIL" parent_team_id="158" avg=".250" hr="0" rbi="2" wins="1" losses="3" era="4.45"/>
		<player id="452733" first="Tom" last="Gorzelanny" num="32" boxname="Gorzelanny" rl="L" position="P" status="A" team_abbrev="MIL" team_id="158" parent_team_abbrev="MIL" parent_team_id="158" avg=".077" hr="0" rbi="0" wins="2" losses="4" era="2.78"/>
		<player id="455117" first="Martin" last="Maldonado" num="12" boxname="Maldonado" rl="R" position="C" current_position="PH" status="A" team_abbrev="MIL" team_id="158" parent_team_abbrev="MIL" parent_team_id="158" avg=".166" hr="3" rbi="16"/>
		<player id="460576" first="Carlos" last="Gomez" num="27" boxname="Gomez, C" rl="R" position="CF" current_position="CF" status="A" team_abbrev="MIL" team_id="158" parent_team_abbrev="MIL" parent_team_id="158" bat_order="5" game_position="CF" avg=".291" hr="18" rbi="54"/>
		<player id="462136" first="Marco" last="Estrada" num="41" boxname="Estrada" rl="R" position="P" current_position="P" status="A" team_abbrev="MIL" team_id="158" parent_team_abbrev="MIL" parent_team_id="158" bat_order="9" game_position="P" avg=".263" hr="0" rbi="2" wins="4" losses="4" era="5.32"/>
		<player id="464433" first="Juan" last="Francisco" num="21" boxname="Francisco, J" rl="R" position="1B" current_position="1B" status="A" team_abbrev="MIL" team_id="158" parent_team_abbrev="MIL" parent_team_id="158" avg=".240" hr="15" rbi="40"/>
		<player id="488674" first="Burke" last="Badenhop" num="31" boxname="Badenhop" rl="R" position="P" current_position="P" status="A" team_abbrev="MIL" team_id="158" parent_team_abbrev="MIL" parent_team_id="158" avg=".000" hr="0" rbi="0" wins="2" losses="3" era="3.86"/>
		<player id="488703" first="Jeff" last="Bianchi" num="14" boxname="Bianchi" rl="R" position="3B" current_position="2B" status="A" team_abbrev="MIL" team_id="158" parent_team_abbrev="MIL" parent_team_id="158" bat_order="8" game_position="3B" avg=".239" hr="0" rbi="16"/>
		<player id="488919" first="Taylor" last="Green" num="5" boxname="Green, T" rl="R" position="3B" status="A" team_abbrev="MIL" team_id="158" parent_team_abbrev="MIL" parent_team_id="158" avg=".000" hr="0" rbi="0"/>
		<player id="493114" first="Norichika" last="Aoki" num="7" boxname="Aoki" rl="R" position="RF" current_position="RF" status="A" team_abbrev="MIL" team_id="158" parent_team_abbrev="MIL" parent_team_id="158" bat_order="2" game_position="RF" avg=".284" hr="6" rbi="23"/>
		<player id="501981" first="Khris" last="Davis" num="18" boxname="Davis, Kh" rl="R" position="LF" current_position="LF" status="A" team_abbrev="MIL" team_id="158" parent_team_abbrev="MIL" parent_team_id="158" bat_order="6" game_position="LF" avg=".258" hr="2" rbi="5"/>
		<player id="502582" first="Logan" last="Schafer" num="22" boxname="Schafer, L" rl="L" position="LF" current_position="PH" status="A" team_abbrev="MIL" team_id="158" parent_team_abbrev="MIL" parent_team_id="158" avg=".230" hr="2" rbi="20"/>
		<player id="503449" first="Wily" last="Peralta" num="60" boxname="Peralta, W" rl="R" position="P" status="A" team_abbrev="MIL" team_id="158" parent_team_abbrev="MIL" parent_team_id="158" avg=".158" hr="0" rbi="0" wins="8" losses="11" era="4.42"/>
		<player id="516416" first="Jean" last="Segura" num="9" boxname="Segura" rl="R" position="SS" current_position="SS" status="A" team_abbrev="MIL" team_id="158" parent_team_abbrev="MIL" parent_team_id="158" bat_order="3" game_position="SS" avg=".314" hr="12" rbi="42"/>
		<player id="518725" first="Caleb" last="Gindl" num="15" boxname="Gindl" rl="L" position="RF" current_position="PH" status="A" team_abbrev="MIL" team_id="158" parent_team_abbrev="MIL" parent_team_id="158" avg=".290" hr="1" rbi="5"/>
		<player id="518764" first="Donovan" last="Hand" num="48" boxname="Hand, D" rl="R" position="P" status="A" team_abbrev="MIL" team_id="158" parent_team_abbrev="MIL" parent_team_id="158" avg=".111" hr="0" rbi="0" wins="0" losses="3" era="3.60"/>
		<player id="518960" first="Jonathan" last="Lucroy" num="20" boxname="Lucroy" rl="R" position="C" current_position="C" status="A" team_abbrev="MIL" team_id="158" parent_team_abbrev="MIL" parent_team_id="158" bat_order="4" game_position="C" avg=".281" hr="16" rbi="60"/>
		<player id="543942" first="Rob" last="Wooten" num="47" boxname="Wooten" rl="R" position="P" status="A" team_abbrev="MIL" team_id="158" parent_team_abbrev="MIL" parent_team_id="158" avg=".000" hr="0" rbi="0" wins="1" losses="0" era="0.00"/>
		<player id="592804" first="Tyler" last="Thornburg" num="63" boxname="Thornburg" rl="R" position="P" status="A" team_abbrev="MIL" team_id="158" parent_team_abbrev="MIL" parent_team_id="158" avg=".000" hr="0" rbi="0" wins="1" losses="0" era="1.78"/>
<coach position="manager" first="Ron" last="Roenicke" id="121373" num="10"/><coach position="hitting_coach" first="Johnny" last="Narron" id="495393" num="13"/><coach position="pitching_coach" first="Rick" last="Kranitz" id="492899" num="39"/><coach position="first_base_coach" first="Garth" last="Iorg" id="116397" num="35"/><coach position="third_base_coach" first="Ed" last="Sedar" id="492532" num="6"/><coach position="bench_coach" first="Jerry" last="Narron" id="119655" num="36"/><coach position="bullpen_coach" first="Lee" last="Tunnell" id="123502" num="43"/><coach position="bullpen_catcher" first="Marcus" last="Hanel" id="438745" num="55"/><coach position="coach" first="John" last="Shelby" id="122112" num="33"/>	</team>
	<team type="home" id="SF" name="San Francisco Giants">
		<player id="217096" first="Barry" last="Zito" num="75" boxname="Zito" rl="L" position="P" current_position="P" status="A" team_abbrev="SF" team_id="137" parent_team_abbrev="SF" parent_team_id="137" avg=".167" hr="0" rbi="2" wins="4" losses="8" era="5.09"/>
		<player id="285064" first="Ryan" last="Vogelsong" num="32" boxname="Vogelsong" rl="R" position="P" status="A" team_abbrev="SF" team_id="137" parent_team_abbrev="SF" parent_team_id="137" avg=".071" hr="0" rbi="2" wins="2" losses="4" era="7.19"/>
		<player id="340192" first="Marco" last="Scutaro" num="19" boxname="Scutaro" rl="R" position="2B" status="A" team_abbrev="SF" team_id="137" parent_team_abbrev="SF" parent_team_id="137" avg=".302" hr="2" rbi="22"/>
		<player id="346793" first="Jeremy" last="Affeldt" num="41" boxname="Affeldt" rl="L" position="P" status="A" team_abbrev="SF" team_id="137" parent_team_abbrev="SF" parent_team_id="137" avg=".000" hr="0" rbi="0" wins="1" losses="4" era="3.51"/>
		<player id="400083" first="Andres" last="Torres" num="56" boxname="Torres, A" rl="R" position="LF" status="A" team_abbrev="SF" team_id="137" parent_team_abbrev="SF" parent_team_id="137" avg=".246" hr="2" rbi="20"/>
		<player id="425565" first="Guillermo" last="Quiroz" num="12" boxname="Quiroz" rl="R" position="C" status="A" team_abbrev="SF" team_id="137" parent_team_abbrev="SF" parent_team_id="137" avg=".186" hr="1" rbi="6"/>
		<player id="425657" first="Javier" last="Lopez" num="49" boxname="Lopez, Ja" rl="L" position="P" status="A" team_abbrev="SF" team_id="137" parent_team_abbrev="SF" parent_team_id="137" avg=".000" hr="0" rbi="0" wins="1" losses="1" era="1.33"/>
		<player id="425796" first="Jeff" last="Francoeur" num="23" boxname="Francoeur" rl="R" position="RF" current_position="CF" status="A" team_abbrev="SF" team_id="137" parent_team_abbrev="SF" parent_team_id="137" bat_order="7" game_position="CF" avg=".213" hr="3" rbi="17"/>
		<player id="429985" first="Chad" last="Gaudin" num="57" boxname="Gaudin" rl="R" position="P" status="A" team_abbrev="SF" team_id="137" parent_team_abbrev="SF" parent_team_id="137" avg=".048" hr="0" rbi="1" wins="5" losses="2" era="2.56"/>
		<player id="430912" first="Matt" last="Cain" num="18" boxname="Cain, M" rl="R" position="P" status="A" team_abbrev="SF" team_id="137" parent_team_abbrev="SF" parent_team_id="137" avg=".079" hr="0" rbi="2" wins="7" losses="7" era="4.47"/>
		<player id="433586" first="Santiago" last="Casilla" num="46" boxname="Casilla, S" rl="R" position="P" current_position="P" status="A" team_abbrev="SF" team_id="137" parent_team_abbrev="SF" parent_team_id="137" avg=".000" hr="0" rbi="0" wins="5" losses="2" era="1.32"/>
		<player id="434636" first="Angel" last="Pagan" num="16" boxname="Pagan" rl="R" position="CF" status="A" team_abbrev="SF" team_id="137" parent_team_abbrev="SF" parent_team_id="137" avg=".262" hr="3" rbi="24"/>
		<player id="435078" first="Joaquin" last="Arias" num="13" boxname="Arias" rl="R" position="3B" current_position="2B" status="A" team_abbrev="SF" team_id="137" parent_team_abbrev="SF" parent_team_id="137" bat_order="8" game_position="2B" avg=".285" hr="0" rbi="13"/>
		<player id="446861" first="Guillermo" last="Moscoso" num="34" boxname="Moscoso" rl="R" position="P" status="A" team_abbrev="SF" team_id="137" parent_team_abbrev="SF" parent_team_id="137" avg=".000" hr="0" rbi="0" wins="0" losses="0" era="6.14"/>
		<player id="452254" first="Hunter" last="Pence" num="8" boxname="Pence" rl="R" position="RF" current_position="RF" status="A" team_abbrev="SF" team_id="137" parent_team_abbrev="SF" parent_team_id="137" bat_order="1" game_position="RF" avg=".277" hr="14" rbi="51"/>
		<player id="453311" first="Tim" last="Lincecum" num="55" boxname="Lincecum" rl="R" position="P" status="A" team_abbrev="SF" team_id="137" parent_team_abbrev="SF" parent_team_id="137" avg=".105" hr="0" rbi="1" wins="5" losses="11" era="4.43"/>
		<player id="453923" first="Gregor" last="Blanco" num="7" boxname="Blanco, G" rl="L" position="LF" current_position="PH" status="A" team_abbrev="SF" team_id="137" parent_team_abbrev="SF" parent_team_id="137" avg=".248" hr="1" rbi="29"/>
		<player id="457763" first="Buster" last="Posey" num="28" boxname="Posey" rl="R" position="C" current_position="C" status="A" team_abbrev="SF" team_id="137" parent_team_abbrev="SF" parent_team_id="137" bat_order="4" game_position="C" avg=".310" hr="14" rbi="60"/>
		<player id="466459" first="Sandy" last="Rosario" num="43" boxname="Rosario, S" rl="R" position="P" status="A" team_abbrev="SF" team_id="137" parent_team_abbrev="SF" parent_team_id="137" avg=".000" hr="0" rbi="0" wins="2" losses="0" era="2.37"/>
		<player id="466948" first="Jean" last="Machi" num="63" boxname="Machi" rl="R" position="P" status="A" team_abbrev="SF" team_id="137" parent_team_abbrev="SF" parent_team_id="137" avg=".000" hr="0" rbi="0" wins="2" losses="1" era="3.34"/>
		<player id="467055" first="Pablo" last="Sandoval" num="48" boxname="Sandoval" rl="R" position="3B" current_position="3B" status="A" team_abbrev="SF" team_id="137" parent_team_abbrev="SF" parent_team_id="137" bat_order="5" game_position="3B" avg=".264" hr="9" rbi="52"/>
		<player id="467726" first="Jose" last="Mijares" num="50" boxname="Mijares" rl="L" position="P" status="A" team_abbrev="SF" team_id="137" parent_team_abbrev="SF" parent_team_id="137" avg=".000" hr="0" rbi="0" wins="0" losses="3" era="2.87"/>
		<player id="473234" first="Tony" last="Abreu" num="10" boxname="Abreu" rl="R" position="2B" status="A" team_abbrev="SF" team_id="137" parent_team_abbrev="SF" parent_team_id="137" avg=".266" hr="1" rbi="7"/>
		<player id="474832" first="Brandon" last="Belt" num="9" boxname="Belt" rl="L" position="1B" current_position="1B" status="A" team_abbrev="SF" team_id="137" parent_team_abbrev="SF" parent_team_id="137" bat_order="3" game_position="1B" avg=".266" hr="11" rbi="41"/>
		<player id="489209" first="Brett" last="Pill" num="6" boxname="Pill" rl="R" position="1B" current_position="PH" status="A" team_abbrev="SF" team_id="137" parent_team_abbrev="SF" parent_team_id="137" avg=".250" hr="2" rbi="7"/>
		<player id="489265" first="Sergio" last="Romo" num="54" boxname="Romo" rl="R" position="P" status="A" team_abbrev="SF" team_id="137" parent_team_abbrev="SF" parent_team_id="137" avg=".000" hr="0" rbi="0" wins="3" losses="6" era="3.02"/>
		<player id="518516" first="Madison" last="Bumgarner" num="40" boxname="Bumgarner" rl="L" position="P" current_position="P" status="A" team_abbrev="SF" team_id="137" parent_team_abbrev="SF" parent_team_id="137" bat_order="9" game_position="P" avg=".132" hr="0" rbi="4" wins="11" losses="6" era="2.69"/>
		<player id="523261" first="Roger" last="Kieschnick" num="22" boxname="Kieschnick" rl="R" position="RF" current_position="LF" status="A" team_abbrev="SF" team_id="137" parent_team_abbrev="SF" parent_team_id="137" bat_order="6" game_position="LF" avg=".381" hr="0" rbi="3"/>
		<player id="543063" first="Brandon" last="Crawford" num="35" boxname="Crawford, B" rl="R" position="SS" current_position="SS" status="A" team_abbrev="SF" team_id="137" parent_team_abbrev="SF" parent_team_id="137" bat_order="2" game_position="SS" avg=".272" hr="7" rbi="36"/>
<coach position="manager" first="Bruce" last="Bochy" id="111136" num="15"/><coach position="batting_coach" first="Hensley" last="Meulens" id="119004" num="31"/><coach position="assistant_hitting_coach" first="Joe" last="Lefebvre" id="117625" num="5"/><coach position="pitching_coach" first="Dave" last="Righetti" id="121201" num="33"/><coach position="first_base_coach" first="Roberto" last="Kelly" id="116959" num="39"/><coach position="third_base_coach" first="Tim" last="Flannery" id="114220" num="1"/><coach position="bench_coach" first="Ron" last="Wotus" id="124588" num="17"/><coach position="bullpen_coach" first="Mark" last="Gardner" id="114610" num="26"/><coach position="bullpen_catcher" first="Bill" last="Hayes" id="115647" num="58"/><coach position="special_assistant" first="Joey" last="Amalfitano" id="110213" num=""/><coach position="special_assistant" first="Jim" last="Davenport" id="113081" num=""/><coach position="special_assistant" first="J.T." last="Snow" id="122497" num=""/>	</team>
<umpires><umpire position="home" name="Bill Welke" id="427534"/><umpire position="first" name="Adrian Johnson" id="482641"/><umpire position="second" name="Brian O'Nora" id="427366"/><umpire position="third" name="Fieldin Culbreth" id="427090"/></umpires></game>